<?xml version="1.0" encoding="UTF-8"?>
<FORM>
  <SUMMARY CRITERIA_SRCH="N" POSITION="TEMPLATE" TITLE="${FORM.SUMMARY.-TITLE}" TMP_SCR_TYPE="M">
    <SUMMARY_BASE></SUMMARY_BASE>
    <SUMMARY_DATA_BLK>BLK_CLASS_DET</SUMMARY_DATA_BLK>
    <SUMBLOCK TABPAGE="QUERY" TYPE="SE" SCREEN="SUMMARY">
      <FIELD TYPE="ME" ID="1">
        <LBL>${FORM.SUMMARY.SUMBLOCK.0.FIELD.0.LBL}</LBL>
        <SIZE>1</SIZE>
        <OPTION VALUE="A">${FORM.SUMMARY.SUMBLOCK.0.FIELD.0.OPTION.0.#text}</OPTION>
        <OPTION VALUE="U">${FORM.SUMMARY.SUMBLOCK.0.FIELD.0.OPTION.1.#text}</OPTION>
        <OPTION VALUE="R">${FORM.SUMMARY.SUMBLOCK.0.FIELD.0.OPTION.2.#text}</OPTION>
        <DTYPE>VARCHAR2</DTYPE>
        <TYPE>SELECT</TYPE>
        <MAXLENGTH>35</MAXLENGTH>
        <CHECKED>N</CHECKED>
        <READ_ONLY>-1</READ_ONLY>
        <NAME>AUTHSTAT</NAME>
      </FIELD>
      <FIELD TYPE="ME" ID="2">
        <LBL>${FORM.SUMMARY.SUMBLOCK.0.FIELD.1.LBL}</LBL>
        <SIZE>1</SIZE>
        <OPTION VALUE="O">${FORM.SUMMARY.SUMBLOCK.0.FIELD.1.OPTION.0.#text}</OPTION>
        <OPTION VALUE="C">${FORM.SUMMARY.SUMBLOCK.0.FIELD.1.OPTION.1.#text}</OPTION>
        <DTYPE>VARCHAR2</DTYPE>
        <TYPE>SELECT</TYPE>
        <MAXLENGTH>35</MAXLENGTH>
        <CHECKED>N</CHECKED>
        <READ_ONLY>-1</READ_ONLY>
        <NAME>TXNSTAT</NAME>
      </FIELD>
      <FIELD TYPE="ME" ID="3">
        <REQD>-1</REQD>
        <LBL>${FORM.SUMMARY.SUMBLOCK.0.FIELD.2.LBL}</LBL>
        <SIZE>12</SIZE>
        <DTYPE>VARCHAR2</DTYPE>
        <TYPE>TEXT</TYPE>
        <MAXLENGTH>10</MAXLENGTH>
        <NAME>CLASCD</NAME>
        <CASE>UPPER</CASE>
      </FIELD>
      <FIELD TYPE="ME" ID="4">
        <LBL>${FORM.SUMMARY.SUMBLOCK.0.FIELD.3.LBL}</LBL>
        <DTYPE>VARCHAR2</DTYPE>
        <TYPE>TEXT</TYPE>
        <MAXLENGTH>105</MAXLENGTH>
        <NAME>CLASDESC</NAME>
      </FIELD>
      <FIELD TYPE="ME" ID="5">
        <REQD>-1</REQD>
        <LBL>${FORM.SUMMARY.SUMBLOCK.0.FIELD.4.LBL}</LBL>
        <SIZE>2</SIZE>
        <DTYPE>VARCHAR2</DTYPE>
        <TYPE>TEXT</TYPE>
        <MAXLENGTH>2</MAXLENGTH>
        <NAME>MOD</NAME>
        <CASE>UPPER</CASE>
      </FIELD>

    </SUMBLOCK>
    <SUMBLOCK TABPAGE="RESULT" TYPE="ME" SCREEN="SUMMARY">
      <FIELD TYPE="ME" ID="1">
        <LBL>${FORM.SUMMARY.SUMBLOCK.1.FIELD.0.LBL}</LBL>
        <SIZE>1</SIZE>
        <OPTION VALUE="A">${FORM.SUMMARY.SUMBLOCK.1.FIELD.0.OPTION.0.#text}</OPTION>
        <OPTION VALUE="U">${FORM.SUMMARY.SUMBLOCK.1.FIELD.0.OPTION.1.#text}</OPTION>
        <OPTION VALUE="R">${FORM.SUMMARY.SUMBLOCK.1.FIELD.0.OPTION.2.#text}</OPTION>
        <DTYPE>VARCHAR2</DTYPE>
        <TYPE>SELECT</TYPE>
        <MAXLENGTH>35</MAXLENGTH>
        <CHECKED>N</CHECKED>
        <READ_ONLY>-1</READ_ONLY>
        <NAME>AUTHSTAT</NAME>
      </FIELD>
      <FIELD TYPE="ME" ID="2">
        <LBL>${FORM.SUMMARY.SUMBLOCK.1.FIELD.1.LBL}</LBL>
        <SIZE>1</SIZE>
        <OPTION VALUE="O">${FORM.SUMMARY.SUMBLOCK.1.FIELD.1.OPTION.0.#text}</OPTION>
        <OPTION VALUE="C">${FORM.SUMMARY.SUMBLOCK.1.FIELD.1.OPTION.1.#text}</OPTION>
        <DTYPE>VARCHAR2</DTYPE>
        <TYPE>SELECT</TYPE>
        <MAXLENGTH>35</MAXLENGTH>
        <CHECKED>N</CHECKED>
        <READ_ONLY>-1</READ_ONLY>
        <NAME>TXNSTAT</NAME>
      </FIELD>
      <FIELD TYPE="ME" ID="3">
        <REQD>-1</REQD>
        <LBL>${FORM.SUMMARY.SUMBLOCK.1.FIELD.2.LBL}</LBL>
        <SIZE>12</SIZE>
        <DTYPE>VARCHAR2</DTYPE>
        <TYPE>TEXT</TYPE>
        <MAXLENGTH>10</MAXLENGTH>
        <NAME>CLASCD</NAME>
        <CASE>UPPER</CASE>
      </FIELD>
      <FIELD TYPE="ME" ID="4">
        <LBL>${FORM.SUMMARY.SUMBLOCK.1.FIELD.3.LBL}</LBL>
        <DTYPE>VARCHAR2</DTYPE>
        <TYPE>TEXT</TYPE>
        <MAXLENGTH>105</MAXLENGTH>
        <NAME>CLASDESC</NAME>
      </FIELD>
      <FIELD TYPE="ME" ID="5">
        <REQD>-1</REQD>
        <LBL>${FORM.SUMMARY.SUMBLOCK.1.FIELD.4.LBL}</LBL>
        <SIZE>2</SIZE>
        <DTYPE>VARCHAR2</DTYPE>
        <TYPE>TEXT</TYPE>
        <MAXLENGTH>2</MAXLENGTH>
        <NAME>MOD</NAME>
        <CASE>UPPER</CASE>
      </FIELD>
      <FIELD TYPE="ME" ID="6">
        <LBL>${FORM.SUMMARY.SUMBLOCK.1.FIELD.5.LBL}</LBL>
        <HIDDEN>-1</HIDDEN>
        <DTYPE>VARCHAR2</DTYPE>
        <TYPE>HIDDEN</TYPE>
        <MAXLENGTH>2</MAXLENGTH>
        <NAME>CLASSTYP</NAME>
      </FIELD>

    </SUMBLOCK>
    <TYPE>S</TYPE>
  </SUMMARY>
  <SCREEN MAIN_WIN="Y" NAME="CVS_MAIN" POSITION="template" TITLE="${FORM.SCREEN.0.-TITLE}" TMP_SCR_TYPE="L">
    <EXIT_BTN>1</EXIT_BTN>
    <HEADER>
      <TAB ID="TAB_HEADER">
        <LBL></LBL>

      </TAB>
    </HEADER>
    <FOOTER>
      <TAB NAME="TAB_FOOTER" HEIGHT="" ID="TAB_FOOTER">
        <LBL></LBL>
        <SECTION NAME="AUDIT_TEMPLATE" ID="AUDIT_TEMPLATE">
          <PART NAME="AUDIT_PART_1" ID="AUDIT_PART_1" WIDTH="50">
            <FLDSET VIEW="SE" TYPE="SE" INDEX="1" ID="FLD_AUDIT1">
              <FIELD SPRT="1" INDEX="1">
                <SIZE>12</SIZE>
                <WIDTH>3</WIDTH>
                <COLS></COLS>
                <MAXLENGTH>12</MAXLENGTH>
                <READ_ONLY>-1</READ_ONLY>
                <NAME>MAKER</NAME>
                <LBL>${FORM.SCREEN.0.FOOTER.TAB.SECTION.PART.FLDSET.FIELD.0.LBL}</LBL>
                <ID>MAKER</ID>
                <DTYPE>VARCHAR2</DTYPE>
                <TYPE>TEXT</TYPE>
                <ROWS></ROWS>
              </FIELD>
              <FIELD INDEX="1" SPRT="1">
                <LBL>${FORM.SCREEN.0.FOOTER.TAB.SECTION.PART.FLDSET.FIELD.1.LBL}</LBL>
                <SIZE>12</SIZE>
                <ID>CHECKER</ID>
                <DTYPE>VARCHAR2</DTYPE>
                <COLS></COLS>
                <TYPE>TEXT</TYPE>
                <MAXLENGTH>12</MAXLENGTH>
                <READ_ONLY>-1</READ_ONLY>
                <NAME>CHECKER</NAME>
                <ROWS></ROWS>
              </FIELD>
              <FIELD SPRT="2" INDEX="2">
                <SIZE>15</SIZE>
                <WIDTH>3</WIDTH>
                <COLS></COLS>
                <MAXLENGTH>15</MAXLENGTH>
                <READ_ONLY>-1</READ_ONLY>
                <NAME>MAKERSTAMP</NAME>
                <LBL>${FORM.SCREEN.0.FOOTER.TAB.SECTION.PART.FLDSET.FIELD.2.LBL}</LBL>
                <ID>MAKERSTAMP</ID>
                <DTYPE>DATE</DTYPE>
                <TYPE>DATETIME</TYPE>
                <ROWS></ROWS>
              </FIELD>
              <FIELD INDEX="2" SPRT="2">
                <LBL>${FORM.SCREEN.0.FOOTER.TAB.SECTION.PART.FLDSET.FIELD.3.LBL}</LBL>
                <SIZE>15</SIZE>
                <ID>CHECKERSTAMP</ID>
                <DTYPE>DATE</DTYPE>
                <COLS></COLS>
                <TYPE>DATETIME</TYPE>
                <MAXLENGTH>15</MAXLENGTH>
                <READ_ONLY>-1</READ_ONLY>
                <NAME>CHECKERSTAMP</NAME>
                <ROWS></ROWS>
              </FIELD>
              <FIELD SPRT="3" INDEX="1">
                <SIZE>4</SIZE>
                <MAX_VAL></MAX_VAL>
                <COLS></COLS>
                <MAXLENGTH>8</MAXLENGTH>
                <READ_ONLY>-1</READ_ONLY>
                <NAME>MODNO</NAME>
                <LBL>${FORM.SCREEN.0.FOOTER.TAB.SECTION.PART.FLDSET.FIELD.4.LBL}</LBL>
                <ID>MODNO</ID>
                <DTYPE>NUMBER</DTYPE>
                <TYPE>TEXT</TYPE>
                <MIN_VAL></MIN_VAL>
                <ROWS></ROWS>
              </FIELD>
              <FIELD SPRT="3" INDEX="2">
                <SIZE>1</SIZE>
                <WIDTH>3</WIDTH>
                <HIDDEN>-1</HIDDEN>
                <COLS></COLS>
                <MAXLENGTH>1</MAXLENGTH>
                <READ_ONLY>-1</READ_ONLY>
                <NAME>ONCEAUTH</NAME>
                <LBL></LBL>
                <ID>ONCEAUTH</ID>
                <DTYPE>VARCHAR</DTYPE>
                <TYPE>HIDDEN</TYPE>
                <ROWS></ROWS>
              </FIELD>
              <FIELD SPRT="4" INDEX="">
                <MAX_DECIMALS></MAX_DECIMALS>
                <SIZE>1</SIZE>
                <OPTION VALUE="" SELECTED="0"></OPTION>
                <OPTION VALUE="C">${FORM.SCREEN.0.FOOTER.TAB.SECTION.PART.FLDSET.FIELD.6.OPTION.1.#text}</OPTION>
                <OPTION VALUE="O">${FORM.SCREEN.0.FOOTER.TAB.SECTION.PART.FLDSET.FIELD.6.OPTION.2.#text}</OPTION>
                <COLS></COLS>
                <CHECKED>N</CHECKED>
                <MAXLENGTH>1</MAXLENGTH>
                <NAME>TXNSTAT</NAME>
                <LBL>${FORM.SCREEN.0.FOOTER.TAB.SECTION.PART.FLDSET.FIELD.6.LBL}</LBL>
                <ID>TXNSTAT</ID>
                <DTYPE>CHAR</DTYPE>
                <TYPE>ROSELECT</TYPE>
                <ROWS></ROWS>
              </FIELD>
              <FIELD SPRT="4" INDEX="">
                <MAX_DECIMALS></MAX_DECIMALS>
                <SIZE>1</SIZE>
                <OPTION VALUE="" SELECTED="0"></OPTION>
                <OPTION VALUE="A">${FORM.SCREEN.0.FOOTER.TAB.SECTION.PART.FLDSET.FIELD.7.OPTION.1.#text}</OPTION>
                <OPTION VALUE="R">${FORM.SCREEN.0.FOOTER.TAB.SECTION.PART.FLDSET.FIELD.7.OPTION.2.#text}</OPTION>
                <OPTION VALUE="U">${FORM.SCREEN.0.FOOTER.TAB.SECTION.PART.FLDSET.FIELD.7.OPTION.3.#text}</OPTION>
                <COLS></COLS>
                <CHECKED>N</CHECKED>
                <MAXLENGTH>1</MAXLENGTH>
                <NAME>AUTHSTAT</NAME>
                <LBL>${FORM.SCREEN.0.FOOTER.TAB.SECTION.PART.FLDSET.FIELD.7.LBL}</LBL>
                <ID>AUTHSTAT</ID>
                <DTYPE>CHAR</DTYPE>
                <TYPE>ROSELECT</TYPE>
                <ROWS></ROWS>
              </FIELD>
              <LBL></LBL>
              <HREQ>0</HREQ>
              <BLOCK>BLK_CLASS_DET</BLOCK>
              <WIDTH></WIDTH>
              <HEIGHT></HEIGHT>
            </FLDSET>
            <SPRTCNT>4</SPRTCNT>

          </PART>
          <LBL></LBL>

        </SECTION>
      </TAB>
    </FOOTER>
    <SUBSCREEN>
      <FORM TYPE="S" SEQ="1" id="CVS_EXPR">
        <SCREEN>CVS_EXPR</SCREEN>
        <LBL>${FORM.SCREEN.0.SUBSCREEN.FORM.0.LBL}</LBL>
        <FUNCTION></FUNCTION>
      </FORM>
      <FORM TYPE="S" SEQ="2" id="CVS_I_EXPR">
        <SCREEN>CVS_I_EXPR</SCREEN>
        <LBL>${FORM.SCREEN.0.SUBSCREEN.FORM.1.LBL}</LBL>
        <FUNCTION></FUNCTION>
      </FORM>
      <FORM TYPE="S" SEQ="3" id="CVS_M_EXPR">
        <SCREEN>CVS_M_EXPR</SCREEN>
        <LBL>${FORM.SCREEN.0.SUBSCREEN.FORM.2.LBL}</LBL>
        <FUNCTION></FUNCTION>
      </FORM>
    </SUBSCREEN>
    <BODY>
      <TAB ID="TAB_MAIN">
        <LBL></LBL>
        <SECTION ID="SEC_COMP" COLLAPSE="N">
          <PART NAME="PART1" ID="PART1" WIDTH="50">
            <FLDSET VIEW="SE" TYPE="SE" INDEX="1" ID="FST_CLASS">
              <FIELD INDEX="" CONTROL="N">
                <REQD>-1</REQD>
                <LBL>${FORM.SCREEN.0.BODY.TAB.SECTION.0.PART.0.FLDSET.FIELD.0.LBL}</LBL>
                <SIZE>12</SIZE>
                <DTYPE>VARCHAR2</DTYPE>
                <COLS></COLS>
                <TYPE>TEXT</TYPE>
                <MAXLENGTH>10</MAXLENGTH>
                <NAME>CLASCD</NAME>
                <CASE>UPPER</CASE>
                <ROWS></ROWS>
              </FIELD>
              <FIELD INDEX="" CONTROL="N">
                <LBL>${FORM.SCREEN.0.BODY.TAB.SECTION.0.PART.0.FLDSET.FIELD.1.LBL}</LBL>
                <SIZE></SIZE>
                <HIDDEN>-1</HIDDEN>
                <DTYPE>VARCHAR2</DTYPE>
                <VALUE>CP</VALUE>
                <COLS></COLS>
                <TYPE>HIDDEN</TYPE>
                <MAXLENGTH>2</MAXLENGTH>
                <NAME>CLASSTYP</NAME>
                <ROWS></ROWS>
              </FIELD>
              <FIELD CONTROL="N" INDEX="">
                <REQD>-1</REQD>
                <SIZE>2</SIZE>
                <COLS></COLS>
                <MAXLENGTH>2</MAXLENGTH>
                <NAME>MOD</NAME>
                <CASE>UPPER</CASE>
                <LOV>
                  <TYPE>L</TYPE>
                  <NAME>LOV_MODULE</NAME>
                </LOV>
                <LBL>${FORM.SCREEN.0.BODY.TAB.SECTION.0.PART.0.FLDSET.FIELD.2.LBL}</LBL>
                <DTYPE>VARCHAR2</DTYPE>
                <TYPE>TEXT</TYPE>
                <ROWS></ROWS>
              </FIELD>
              <LBL></LBL>
              <HREQ>0</HREQ>
              <BLOCK>BLK_CLASS_DET</BLOCK>
              <WIDTH></WIDTH>
              <HEIGHT></HEIGHT>
            </FLDSET>

          </PART>
          <PART NAME="PART2" ID="PART2" WIDTH="50">
            <FLDSET VIEW="SE" TYPE="SE" INDEX="1" ID="FST_CLASS_DESC">
              <FIELD INDEX="" CONTROL="N">
                <POPUPEDIT>
                  <OK_IMG_SRC></OK_IMG_SRC>
                  <TITLE>${FORM.SCREEN.0.BODY.TAB.SECTION.0.PART.1.FLDSET.FIELD.POPUPEDIT.TITLE}</TITLE>
                  <CANCEL_IMG_SRC></CANCEL_IMG_SRC>
                </POPUPEDIT>
                <LBL>${FORM.SCREEN.0.BODY.TAB.SECTION.0.PART.1.FLDSET.FIELD.LBL}</LBL>
                <SIZE></SIZE>
                <DTYPE>VARCHAR2</DTYPE>
                <COLS></COLS>
                <TYPE>TEXT</TYPE>
                <MAXLENGTH>105</MAXLENGTH>
                <NAME>CLASDESC</NAME>
                <ROWS></ROWS>
              </FIELD>
              <LBL></LBL>
              <HREQ>0</HREQ>
              <BLOCK>BLK_CLASS_DET</BLOCK>
              <WIDTH></WIDTH>
              <HEIGHT></HEIGHT>
            </FLDSET>

          </PART>
          <LBL></LBL>

        </SECTION>
        <SECTION ID="SEC_COMP1" COLLAPSE="N">
          <PART NAME="PART1" ID="PART1" WIDTH="33">
            <FLDSET VIEW="SE" TYPE="ME" INDEX="1" ID="FST_MORI">
              <FIELD CONTROL="N" INDEX="">
                <MAX_DECIMALS></MAX_DECIMALS>
                <SIZE></SIZE>
                <MAX_VAL></MAX_VAL>
                <COLS></COLS>
                <MAXLENGTH>22</MAXLENGTH>
                <NAME>MORPERD</NAME>
                <LBL>${FORM.SCREEN.0.BODY.TAB.SECTION.1.PART.0.FLDSET.0.FIELD.0.LBL}</LBL>
                <DTYPE>NUMBER</DTYPE>
                <TYPE>TEXT</TYPE>
                <MIN_VAL></MIN_VAL>
                <ROWS></ROWS>
              </FIELD>
              <FIELD INDEX="" CONTROL="N">
                <LBL>${FORM.SCREEN.0.BODY.TAB.SECTION.1.PART.0.FLDSET.0.FIELD.1.LBL}</LBL>
                <SIZE></SIZE>
                <OPTION VALUE="D" SELECTED="0">${FORM.SCREEN.0.BODY.TAB.SECTION.1.PART.0.FLDSET.0.FIELD.1.OPTION.0.#text}</OPTION>
                <OPTION VALUE="M" SELECTED="0">${FORM.SCREEN.0.BODY.TAB.SECTION.1.PART.0.FLDSET.0.FIELD.1.OPTION.1.#text}</OPTION>
                <OPTION VALUE="Y" SELECTED="0">${FORM.SCREEN.0.BODY.TAB.SECTION.1.PART.0.FLDSET.0.FIELD.1.OPTION.2.#text}</OPTION>
                <OPTION VALUE="" SELECTED="-1"></OPTION>
                <DTYPE>VARCHAR2</DTYPE>
                <COLS></COLS>
                <TYPE>SELECT</TYPE>
                <MAXLENGTH>1</MAXLENGTH>
                <NAME>MORPERDUN</NAME>
                <ROWS></ROWS>
              </FIELD>
              <LBL>${FORM.SCREEN.0.BODY.TAB.SECTION.1.PART.0.FLDSET.0.LBL}</LBL>
              <HREQ>0</HREQ>
              <BLOCK>BLK_COMPONENT_DET</BLOCK>
              <WIDTH></WIDTH>
              <HEIGHT></HEIGHT>
            </FLDSET>
            <FLDSET VIEW="SE" TYPE="ME" INDEX="2" ID="FST_PREPAYTH">
              <FIELD CONTROL="N" INDEX="">
                <SIZE></SIZE>
                <COLS></COLS>
                <MAXLENGTH>3</MAXLENGTH>
                <READ_ONLY>-1</READ_ONLY>
                <NAME>PRPMTTHCCY</NAME>
                <CASE>UPPER</CASE>
                <LOV>
                  <TYPE>L</TYPE>
                  <NAME>LOV_PREP_CCY</NAME>
                </LOV>
                <LBL>${FORM.SCREEN.0.BODY.TAB.SECTION.1.PART.0.FLDSET.1.FIELD.0.LBL}</LBL>
                <INPUT_LOV>-1</INPUT_LOV>
                <DTYPE>VARCHAR2</DTYPE>
                <TYPE>TEXT</TYPE>
                <ROWS></ROWS>
              </FIELD>
              <FIELD CONTROL="N" INDEX="">
                <MAX_DECIMALS></MAX_DECIMALS>
                <SIZE></SIZE>
                <MAX_VAL></MAX_VAL>
                <COLS></COLS>
                <RELATED_FIELD>PRPMTTHCCY</RELATED_FIELD>
                <MAXLENGTH>22</MAXLENGTH>
                <NAME>PRPMTTHAMT</NAME>
                <LBL>${FORM.SCREEN.0.BODY.TAB.SECTION.1.PART.0.FLDSET.1.FIELD.1.LBL}</LBL>
                <DTYPE>NUMBER</DTYPE>
                <TYPE>AMOUNT</TYPE>
                <MIN_VAL></MIN_VAL>
                <ROWS></ROWS>
              </FIELD>
              <LBL>${FORM.SCREEN.0.BODY.TAB.SECTION.1.PART.0.FLDSET.1.LBL}</LBL>
              <HREQ>0</HREQ>
              <BLOCK>BLK_COMPONENT_DET</BLOCK>
              <WIDTH></WIDTH>
              <HEIGHT></HEIGHT>
            </FLDSET>

          </PART>
          <PART NAME="PART2" ID="PART2" WIDTH="66">
            <FLDSET VIEW="SE" TYPE="ME" INDEX="1" ID="FST_COMPDF">
              <NAV_BTN_REQ>Y</NAV_BTN_REQ>
              <FIELD INDEX="" CONTROL="N" SPRT="1">
                <LBL>${FORM.SCREEN.0.BODY.TAB.SECTION.1.PART.1.FLDSET.FIELD.0.LBL}</LBL>
                <SIZE></SIZE>
                <DTYPE>VARCHAR2</DTYPE>
                <COLS></COLS>
                <TYPE>TEXT</TYPE>
                <MAXLENGTH>20</MAXLENGTH>
                <NAME>CMPNAME</NAME>
                <CASE>UPPER</CASE>
                <ROWS></ROWS>
              </FIELD>
              <FIELD CONTROL="N" SPRT="2" INDEX="">
                <SIZE></SIZE>
                <COLS></COLS>
                <CHECKED>N</CHECKED>
                <MAXLENGTH>1</MAXLENGTH>
                <NAME>MAINCMP</NAME>
                <LBL>${FORM.SCREEN.0.BODY.TAB.SECTION.1.PART.1.FLDSET.FIELD.1.LBL}</LBL>
                <CUSTOM>
                  <OFF>N</OFF>
                  <ON>Y</ON>
                </CUSTOM>
                <DTYPE>VARCHAR2</DTYPE>
                <TYPE>CHECKBOX</TYPE>
                <ROWS></ROWS>
              </FIELD>
              <FIELD INDEX="" CONTROL="N" SPRT="1">
                <LBL>${FORM.SCREEN.0.BODY.TAB.SECTION.1.PART.1.FLDSET.FIELD.2.LBL}</LBL>
                <SIZE></SIZE>
                <DTYPE>VARCHAR2</DTYPE>
                <COLS></COLS>
                <TYPE>TEXT</TYPE>
                <MAXLENGTH>100</MAXLENGTH>
                <NAME>CMPDESC</NAME>
                <ROWS></ROWS>
              </FIELD>
              <FIELD CONTROL="N" SPRT="2" INDEX="">
                <SIZE></SIZE>
                <VALUE>N</VALUE>
                <COLS></COLS>
                <CHECKED>N</CHECKED>
                <MAXLENGTH>1</MAXLENGTH>
                <NAME>CAP</NAME>
                <LBL>${FORM.SCREEN.0.BODY.TAB.SECTION.1.PART.1.FLDSET.FIELD.3.LBL}</LBL>
                <CUSTOM>
                  <OFF>N</OFF>
                  <ON>Y</ON>
                </CUSTOM>
                <DTYPE>VARCHAR2</DTYPE>
                <TYPE>CHECKBOX</TYPE>
                <ROWS></ROWS>
              </FIELD>
              <FIELD INDEX="" CONTROL="N" SPRT="2">
                <LBL>${FORM.SCREEN.0.BODY.TAB.SECTION.1.PART.1.FLDSET.FIELD.4.LBL}</LBL>
                <SIZE></SIZE>
                <HIDDEN>-1</HIDDEN>
                <DTYPE>VARCHAR2</DTYPE>
                <COLS></COLS>
                <TYPE>HIDDEN</TYPE>
                <MAXLENGTH>2</MAXLENGTH>
                <NAME>CMPREPTYPE</NAME>
                <ROWS></ROWS>
              </FIELD>
              <FIELD CONTROL="N" SPRT="1" INDEX="">
                <SIZE></SIZE>
                <COLS></COLS>
                <MAXLENGTH>3</MAXLENGTH>
                <NAME>CMPCCY</NAME>
                <CASE>UPPER</CASE>
                <LOV>
                  <TYPE>L</TYPE>
                  <NAME>LOV_COMP_CCY</NAME>
                </LOV>
                <LBL>${FORM.SCREEN.0.BODY.TAB.SECTION.1.PART.1.FLDSET.FIELD.5.LBL}</LBL>
                <DTYPE>VARCHAR2</DTYPE>
                <TYPE>TEXT</TYPE>
                <ROWS></ROWS>
              </FIELD>
              <FIELD CONTROL="N" SPRT="2" INDEX="">
                <SIZE></SIZE>
                <VALUE>N</VALUE>
                <COLS></COLS>
                <CHECKED>N</CHECKED>
                <MAXLENGTH>1</MAXLENGTH>
                <NAME>INTPOSTREQ</NAME>
                <LBL>${FORM.SCREEN.0.BODY.TAB.SECTION.1.PART.1.FLDSET.FIELD.6.LBL}</LBL>
                <CUSTOM>
                  <OFF>N</OFF>
                  <ON>Y</ON>
                </CUSTOM>
                <DTYPE>VARCHAR2</DTYPE>
                <TYPE>CHECKBOX</TYPE>
                <ROWS></ROWS>
              </FIELD>
              <FIELD INDEX="" CONTROL="N" SPRT="1">
                <LBL>${FORM.SCREEN.0.BODY.TAB.SECTION.1.PART.1.FLDSET.FIELD.7.LBL}</LBL>
                <SIZE></SIZE>
                <OPTION VALUE="I" SELECTED="0">${FORM.SCREEN.0.BODY.TAB.SECTION.1.PART.1.FLDSET.FIELD.7.OPTION.0.#text}</OPTION>
                <OPTION VALUE="H" SELECTED="0">${FORM.SCREEN.0.BODY.TAB.SECTION.1.PART.1.FLDSET.FIELD.7.OPTION.1.#text}</OPTION>
                <OPTION VALUE="P" SELECTED="0">${FORM.SCREEN.0.BODY.TAB.SECTION.1.PART.1.FLDSET.FIELD.7.OPTION.2.#text}</OPTION>
                <OPTION VALUE="M" SELECTED="0">${FORM.SCREEN.0.BODY.TAB.SECTION.1.PART.1.FLDSET.FIELD.7.OPTION.3.#text}</OPTION>
                <OPTION VALUE="D" SELECTED="0">${FORM.SCREEN.0.BODY.TAB.SECTION.1.PART.1.FLDSET.FIELD.7.OPTION.4.#text}</OPTION>
                <OPTION VALUE="L" SELECTED="0">${FORM.SCREEN.0.BODY.TAB.SECTION.1.PART.1.FLDSET.FIELD.7.OPTION.5.#text}</OPTION>
                <OPTION VALUE="O" SELECTED="0">${FORM.SCREEN.0.BODY.TAB.SECTION.1.PART.1.FLDSET.FIELD.7.OPTION.6.#text}</OPTION>
                <OPTION VALUE="F" SELECTED="0">${FORM.SCREEN.0.BODY.TAB.SECTION.1.PART.1.FLDSET.FIELD.7.OPTION.7.#text}</OPTION>
                <OPTION VALUE="G" SELECTED="0">${FORM.SCREEN.0.BODY.TAB.SECTION.1.PART.1.FLDSET.FIELD.7.OPTION.8.#text}</OPTION>
                <OPTION VALUE="S" SELECTED="0">${FORM.SCREEN.0.BODY.TAB.SECTION.1.PART.1.FLDSET.FIELD.7.OPTION.9.#text}</OPTION>
                <OPTION VALUE="" SELECTED="-1"></OPTION>
                <OPTION VALUE="R" SELECTED="0">${FORM.SCREEN.0.BODY.TAB.SECTION.1.PART.1.FLDSET.FIELD.7.OPTION.11.#text}</OPTION>
                <DTYPE>VARCHAR2</DTYPE>
                <COLS></COLS>
                <TYPE>SELECT</TYPE>
                <MAXLENGTH>1</MAXLENGTH>
                <NAME>CMPTYPE</NAME>
                <ROWS></ROWS>
              </FIELD>
              <FIELD INDEX="" CONTROL="N" SPRT="2">
                <LOV>
                  <TYPE>L</TYPE>
                  <NAME>LOV_REP_TYPE</NAME>
                </LOV>
                <LBL>${FORM.SCREEN.0.BODY.TAB.SECTION.1.PART.1.FLDSET.FIELD.8.LBL}</LBL>
                <SIZE></SIZE>
                <DTYPE>VARCHAR2</DTYPE>
                <COLS></COLS>
                <TYPE>TEXT</TYPE>
                <MAXLENGTH>35</MAXLENGTH>
                <NAME>REPTYPE</NAME>
                <ROWS></ROWS>
              </FIELD>
              <FIELD CONTROL="N" SPRT="2" INDEX="">
                <SIZE></SIZE>
                <COLS></COLS>
                <CHECKED>N</CHECKED>
                <MAXLENGTH>1</MAXLENGTH>
                <NAME>PROPREQ</NAME>
                <LBL>${FORM.SCREEN.0.BODY.TAB.SECTION.1.PART.1.FLDSET.FIELD.9.LBL}</LBL>
                <CUSTOM>
                  <OFF>N</OFF>
                  <ON>Y</ON>
                </CUSTOM>
                <DTYPE>VARCHAR2</DTYPE>
                <TYPE>CHECKBOX</TYPE>
                <ROWS></ROWS>
              </FIELD>
              <FIELD CONTROL="N" SPRT="1" INDEX="">
                <SIZE></SIZE>
                <COLS></COLS>
                <CHECKED>N</CHECKED>
                <MAXLENGTH>1</MAXLENGTH>
                <NAME>INCLUDEINEMI</NAME>
                <LBL>${FORM.SCREEN.0.BODY.TAB.SECTION.1.PART.1.FLDSET.FIELD.10.LBL}</LBL>
                <CUSTOM>
                  <OFF>N</OFF>
                  <ON>Y</ON>
                </CUSTOM>
                <DTYPE>VARCHAR2</DTYPE>
                <TYPE>CHECKBOX</TYPE>
                <ROWS></ROWS>
              </FIELD>
              <FIELD CONTROL="N" SPRT="2" INDEX="">
                <SIZE></SIZE>
                <VALUE>N</VALUE>
                <COLS></COLS>
                <CHECKED>N</CHECKED>
                <MAXLENGTH>1</MAXLENGTH>
                <NAME>EXP_FLAG</NAME>
                <LBL>${FORM.SCREEN.0.BODY.TAB.SECTION.1.PART.1.FLDSET.FIELD.11.LBL}</LBL>
                <CUSTOM>
                  <OFF>N</OFF>
                  <ON>Y</ON>
                </CUSTOM>
                <DTYPE>CHAR</DTYPE>
                <TYPE>CHECKBOX</TYPE>
                <ROWS></ROWS>
              </FIELD>
              <FIELD CONTROL="N" SPRT="2" INDEX="">
                <SIZE></SIZE>
                <COLS></COLS>
                <CHECKED>N</CHECKED>
                <MAXLENGTH>1</MAXLENGTH>
                <NAME>RESCH_FLAG</NAME>
                <LBL>${FORM.SCREEN.0.BODY.TAB.SECTION.1.PART.1.FLDSET.FIELD.12.LBL}</LBL>
                <CUSTOM>
                  <OFF>N</OFF>
                  <ON>Y</ON>
                </CUSTOM>
                <DTYPE>VARCHAR2</DTYPE>
                <TYPE>CHECKBOX</TYPE>
                <ROWS></ROWS>
              </FIELD>
              <FIELD CONTROL="N" SPRT="2" INDEX="">
                <SIZE></SIZE>
                <COLS></COLS>
                <CHECKED>N</CHECKED>
                <MAXLENGTH>1</MAXLENGTH>
                <NAME>BOOK_UNEARNED_PROFIT</NAME>
                <LBL>${FORM.SCREEN.0.BODY.TAB.SECTION.1.PART.1.FLDSET.FIELD.13.LBL}</LBL>
                <CUSTOM>
                  <OFF>N</OFF>
                  <ON>Y</ON>
                </CUSTOM>
                <DTYPE>VARCHAR2</DTYPE>
                <TYPE>CHECKBOX</TYPE>
                <ROWS></ROWS>
              </FIELD>
              <LBL>${FORM.SCREEN.0.BODY.TAB.SECTION.1.PART.1.FLDSET.LBL}</LBL>
              <HREQ>0</HREQ>
              <BLOCK>BLK_COMPONENT_DET</BLOCK>
              <WIDTH></WIDTH>
              <HEIGHT></HEIGHT>
            </FLDSET>
            <SPRTCNT>2</SPRTCNT>

          </PART>
          <LBL></LBL>

        </SECTION>
        <SECTION ID="SEC_COMP2" COLLAPSE="N">
          <PART NAME="PART1" ID="PART1" WIDTH="33">
            <FLDSET VIEW="SE" TYPE="ME" INDEX="1" ID="FST_CMPDF">
              <FIELD INDEX="" CONTROL="N">
                <LBL>${FORM.SCREEN.0.BODY.TAB.SECTION.2.PART.0.FLDSET.FIELD.0.LBL}</LBL>
                <SIZE></SIZE>
                <CUSTOM>
                  <OFF>N</OFF>
                  <ON>Y</ON>
                </CUSTOM>
                <DTYPE>VARCHAR2</DTYPE>
                <COLS></COLS>
                <TYPE>CHECKBOX</TYPE>
                <CHECKED>N</CHECKED>
                <MAXLENGTH>1</MAXLENGTH>
                <NAME>SPLINT</NAME>
                <ROWS></ROWS>
              </FIELD>
              <FIELD INDEX="" CONTROL="N">
                <LBL>${FORM.SCREEN.0.BODY.TAB.SECTION.2.PART.0.FLDSET.FIELD.1.LBL}</LBL>
                <SIZE></SIZE>
                <OPTION VALUE="D" SELECTED="0">${FORM.SCREEN.0.BODY.TAB.SECTION.2.PART.0.FLDSET.FIELD.1.OPTION.0.#text}</OPTION>
                <OPTION VALUE="P" SELECTED="0">${FORM.SCREEN.0.BODY.TAB.SECTION.2.PART.0.FLDSET.FIELD.1.OPTION.1.#text}</OPTION>
                <OPTION VALUE="" SELECTED="-1"></OPTION>
                <DTYPE>VARCHAR2</DTYPE>
                <COLS></COLS>
                <TYPE>SELECT</TYPE>
                <MAXLENGTH>1</MAXLENGTH>
                <NAME>PERIODICITY</NAME>
                <CASE>UPPER</CASE>
                <ROWS></ROWS>
              </FIELD>
              <FIELD INDEX="" CONTROL="N">
                <LBL>${FORM.SCREEN.0.BODY.TAB.SECTION.2.PART.0.FLDSET.FIELD.2.LBL}</LBL>
                <SIZE></SIZE>
                <OPTION COL="1" ROW="LBL_DEBIT">
                  <SELECTED>0</SELECTED>
                  <LBL>${FORM.SCREEN.0.BODY.TAB.SECTION.2.PART.0.FLDSET.FIELD.2.OPTION.0.LBL}</LBL>
                  <ID>D</ID>
                  <VALUE>D</VALUE>
                </OPTION>
                <OPTION COL="1" ROW="LBL_CREDIT">
                  <SELECTED>0</SELECTED>
                  <LBL>${FORM.SCREEN.0.BODY.TAB.SECTION.2.PART.0.FLDSET.FIELD.2.OPTION.1.LBL}</LBL>
                  <ID>C</ID>
                  <VALUE>C</VALUE>
                </OPTION>
                <DTYPE>VARCHAR2</DTYPE>
                <COLS></COLS>
                <TYPE>RADIO</TYPE>
                <MAXLENGTH>1</MAXLENGTH>
                <NAME>BALTYPE</NAME>
                <ROWS></ROWS>
              </FIELD>
              <FIELD INDEX="" CONTROL="N">
                <LBL>${FORM.SCREEN.0.BODY.TAB.SECTION.2.PART.0.FLDSET.FIELD.3.LBL}</LBL>
                <SIZE></SIZE>
                <CUSTOM>
                  <OFF>N</OFF>
                  <ON>Y</ON>
                </CUSTOM>
                <DTYPE>VARCHAR2</DTYPE>
                <COLS></COLS>
                <TYPE>CHECKBOX</TYPE>
                <CHECKED>N</CHECKED>
                <MAXLENGTH>4</MAXLENGTH>
                <NAME>TRACK_RECEIVABLE</NAME>
                <ROWS></ROWS>
              </FIELD>
              <FIELD INDEX="" CONTROL="N">
                <LBL>${FORM.SCREEN.0.BODY.TAB.SECTION.2.PART.0.FLDSET.FIELD.4.LBL}</LBL>
                <SIZE></SIZE>
                <CUSTOM>
                  <OFF>N</OFF>
                  <ON>Y</ON>
                </CUSTOM>
                <DTYPE>VARCHAR2</DTYPE>
                <COLS></COLS>
                <TYPE>CHECKBOX</TYPE>
                <CHECKED>N</CHECKED>
                <MAXLENGTH>4</MAXLENGTH>
                <NAME>TRACK_PAYABLE</NAME>
                <ROWS></ROWS>
              </FIELD>
              <FIELD INDEX="" CONTROL="N">
                <LBL>${FORM.SCREEN.0.BODY.TAB.SECTION.2.PART.0.FLDSET.FIELD.5.LBL}</LBL>
                <SIZE></SIZE>
                <OPTION VALUE="5" SELECTED="0">${FORM.SCREEN.0.BODY.TAB.SECTION.2.PART.0.FLDSET.FIELD.5.OPTION.0.#text}</OPTION>
                <OPTION VALUE="6" SELECTED="0">${FORM.SCREEN.0.BODY.TAB.SECTION.2.PART.0.FLDSET.FIELD.5.OPTION.1.#text}</OPTION>
                <OPTION VALUE="3" SELECTED="0">${FORM.SCREEN.0.BODY.TAB.SECTION.2.PART.0.FLDSET.FIELD.5.OPTION.2.#text}</OPTION>
                <OPTION VALUE="8" SELECTED="0">${FORM.SCREEN.0.BODY.TAB.SECTION.2.PART.0.FLDSET.FIELD.5.OPTION.3.#text}</OPTION>
                <OPTION VALUE="1" SELECTED="0">${FORM.SCREEN.0.BODY.TAB.SECTION.2.PART.0.FLDSET.FIELD.5.OPTION.4.#text}</OPTION>
                <OPTION VALUE="4" SELECTED="0">${FORM.SCREEN.0.BODY.TAB.SECTION.2.PART.0.FLDSET.FIELD.5.OPTION.5.#text}</OPTION>
                <OPTION VALUE="7" SELECTED="0">${FORM.SCREEN.0.BODY.TAB.SECTION.2.PART.0.FLDSET.FIELD.5.OPTION.6.#text}</OPTION>
                <OPTION VALUE="C" SELECTED="0">${FORM.SCREEN.0.BODY.TAB.SECTION.2.PART.0.FLDSET.FIELD.5.OPTION.7.#text}</OPTION>
                <OPTION VALUE="10" SELECTED="0">${FORM.SCREEN.0.BODY.TAB.SECTION.2.PART.0.FLDSET.FIELD.5.OPTION.8.#text}</OPTION>
                <OPTION VALUE="11" SELECTED="0">${FORM.SCREEN.0.BODY.TAB.SECTION.2.PART.0.FLDSET.FIELD.5.OPTION.9.#text}</OPTION>
                <OPTION VALUE="0" SELECTED="0">${FORM.SCREEN.0.BODY.TAB.SECTION.2.PART.0.FLDSET.FIELD.5.OPTION.10.#text}</OPTION>
                <OPTION VALUE="13" SELECTED="0">${FORM.SCREEN.0.BODY.TAB.SECTION.2.PART.0.FLDSET.FIELD.5.OPTION.11.#text}</OPTION>
                <OPTION VALUE="12" SELECTED="0">${FORM.SCREEN.0.BODY.TAB.SECTION.2.PART.0.FLDSET.FIELD.5.OPTION.12.#text}</OPTION>
                <OPTION VALUE="14" SELECTED="0">${FORM.SCREEN.0.BODY.TAB.SECTION.2.PART.0.FLDSET.FIELD.5.OPTION.13.#text}</OPTION>
                <OPTION VALUE="15" SELECTED="0">${FORM.SCREEN.0.BODY.TAB.SECTION.2.PART.0.FLDSET.FIELD.5.OPTION.14.#text}</OPTION>
                <OPTION VALUE="" SELECTED="-1"></OPTION>
                <DTYPE>VARCHAR2</DTYPE>
                <COLS></COLS>
                <TYPE>SELECT</TYPE>
                <MAXLENGTH>2</MAXLENGTH>
                <NAME>FRMTYP</NAME>
                <ROWS></ROWS>
              </FIELD>
              <LBL>${FORM.SCREEN.0.BODY.TAB.SECTION.2.PART.0.FLDSET.LBL}</LBL>
              <HREQ>0</HREQ>
              <BLOCK>BLK_COMPONENT_DET</BLOCK>
              <WIDTH></WIDTH>
              <HEIGHT></HEIGHT>
            </FLDSET>

          </PART>
          <PART NAME="PART2" ID="PART2" WIDTH="33">
            <FLDSET VIEW="SE" TYPE="ME" INDEX="1" ID="FST_COMPAT">
              <FIELD INDEX="" CONTROL="N">
                <LBL>${FORM.SCREEN.0.BODY.TAB.SECTION.2.PART.1.FLDSET.FIELD.0.LBL}</LBL>
                <SIZE></SIZE>
                <OPTION VALUE="3" SELECTED="-1">${FORM.SCREEN.0.BODY.TAB.SECTION.2.PART.1.FLDSET.FIELD.0.OPTION.0.#text}</OPTION>
                <OPTION VALUE="1" SELECTED="0">${FORM.SCREEN.0.BODY.TAB.SECTION.2.PART.1.FLDSET.FIELD.0.OPTION.1.#text}</OPTION>
                <OPTION VALUE="2" SELECTED="0">${FORM.SCREEN.0.BODY.TAB.SECTION.2.PART.1.FLDSET.FIELD.0.OPTION.2.#text}</OPTION>
                <OPTION VALUE="4" SELECTED="0">${FORM.SCREEN.0.BODY.TAB.SECTION.2.PART.1.FLDSET.FIELD.0.OPTION.3.#text}</OPTION>
                <OPTION VALUE="A" SELECTED="0">${FORM.SCREEN.0.BODY.TAB.SECTION.2.PART.1.FLDSET.FIELD.0.OPTION.4.#text}</OPTION>
                <OPTION VALUE="" SELECTED="0"></OPTION>
                <DTYPE>VARCHAR2</DTYPE>
                <VALUE>3</VALUE>
                <COLS></COLS>
                <TYPE>SELECT</TYPE>
                <MAXLENGTH>1</MAXLENGTH>
                <NAME>DAYSMTH</NAME>
                <ROWS></ROWS>
              </FIELD>
              <FIELD INDEX="" CONTROL="N">
                <LBL>${FORM.SCREEN.0.BODY.TAB.SECTION.2.PART.1.FLDSET.FIELD.1.LBL}</LBL>
                <SIZE></SIZE>
                <OPTION VALUE="1" SELECTED="0">${FORM.SCREEN.0.BODY.TAB.SECTION.2.PART.1.FLDSET.FIELD.1.OPTION.0.#text}</OPTION>
                <OPTION VALUE="2" SELECTED="0">${FORM.SCREEN.0.BODY.TAB.SECTION.2.PART.1.FLDSET.FIELD.1.OPTION.1.#text}</OPTION>
                <OPTION VALUE="3" SELECTED="-1">${FORM.SCREEN.0.BODY.TAB.SECTION.2.PART.1.FLDSET.FIELD.1.OPTION.2.#text}</OPTION>
                <OPTION VALUE="4" SELECTED="0">${FORM.SCREEN.0.BODY.TAB.SECTION.2.PART.1.FLDSET.FIELD.1.OPTION.3.#text}</OPTION>
                <OPTION VALUE="" SELECTED="0"></OPTION>
                <DTYPE>VARCHAR2</DTYPE>
                <VALUE>3</VALUE>
                <COLS></COLS>
                <TYPE>SELECT</TYPE>
                <MAXLENGTH>1</MAXLENGTH>
                <NAME>DAYSYR</NAME>
                <ROWS></ROWS>
              </FIELD>
              <FIELD CONTROL="N" INDEX="">
                <MAX_DECIMALS></MAX_DECIMALS>
                <SIZE></SIZE>
                <MAX_VAL></MAX_VAL>
                <COLS></COLS>
                <MAXLENGTH>22</MAXLENGTH>
                <NAME>GRCDAYS</NAME>
                <LBL>${FORM.SCREEN.0.BODY.TAB.SECTION.2.PART.1.FLDSET.FIELD.2.LBL}</LBL>
                <DTYPE>NUMBER</DTYPE>
                <TYPE>TEXT</TYPE>
                <MIN_VAL></MIN_VAL>
                <ROWS></ROWS>
              </FIELD>
              <FIELD INDEX="" CONTROL="N">
                <LBL>${FORM.SCREEN.0.BODY.TAB.SECTION.2.PART.1.FLDSET.FIELD.3.LBL}</LBL>
                <SIZE></SIZE>
                <CUSTOM>
                  <OFF>N</OFF>
                  <ON>Y</ON>
                </CUSTOM>
                <DTYPE>VARCHAR2</DTYPE>
                <COLS></COLS>
                <TYPE>CHECKBOX</TYPE>
                <CHECKED>N</CHECKED>
                <MAXLENGTH>1</MAXLENGTH>
                <NAME>VERFUNDS</NAME>
                <ROWS></ROWS>
              </FIELD>
              <FIELD INDEX="" CONTROL="N">
                <LBL>${FORM.SCREEN.0.BODY.TAB.SECTION.2.PART.1.FLDSET.FIELD.4.LBL}</LBL>
                <SIZE></SIZE>
                <CUSTOM>
                  <OFF>N</OFF>
                  <ON>Y</ON>
                </CUSTOM>
                <DTYPE>VARCHAR2</DTYPE>
                <COLS></COLS>
                <TYPE>CHECKBOX</TYPE>
                <CHECKED>N</CHECKED>
                <MAXLENGTH>1</MAXLENGTH>
                <NAME>DAYSFRMCCY</NAME>
                <ROWS></ROWS>
              </FIELD>
              <FIELD CONTROL="N" INDEX="">
                <SIZE></SIZE>
                <VALUE>N</VALUE>
                <COLS></COLS>
                <CHECKED>N</CHECKED>
                <MAXLENGTH>1</MAXLENGTH>
                <NAME>IRRAPP</NAME>
                <LBL>${FORM.SCREEN.0.BODY.TAB.SECTION.2.PART.1.FLDSET.FIELD.5.LBL}</LBL>
                <CUSTOM>
                  <OFF>N</OFF>
                  <ON>Y</ON>
                </CUSTOM>
                <DTYPE>CHAR</DTYPE>
                <TYPE>CHECKBOX</TYPE>
                <ROWS></ROWS>
              </FIELD>
              <FIELD CONTROL="N" INDEX="">
                <SIZE></SIZE>
                <VALUE>N</VALUE>
                <COLS></COLS>
                <CHECKED>N</CHECKED>
                <MAXLENGTH>1</MAXLENGTH>
                <NAME>NEGATIVEINTEREST</NAME>
                <LBL>${FORM.SCREEN.0.BODY.TAB.SECTION.2.PART.1.FLDSET.FIELD.6.LBL}</LBL>
                <CUSTOM>
                  <OFF>N</OFF>
                  <ON>Y</ON>
                </CUSTOM>
                <DTYPE>VARCHAR2</DTYPE>
                <TYPE>CHECKBOX</TYPE>
                <ROWS></ROWS>
              </FIELD>
              <LBL>${FORM.SCREEN.0.BODY.TAB.SECTION.2.PART.1.FLDSET.LBL}</LBL>
              <HREQ>0</HREQ>
              <BLOCK>BLK_COMPONENT_DET</BLOCK>
              <WIDTH></WIDTH>
              <HEIGHT></HEIGHT>
            </FLDSET>

          </PART>
          <PART NAME="PART3" ID="PART3" WIDTH="33">
            <FLDSET VIEW="SE" TYPE="ME" INDEX="1" ID="FST_ACCPROV">
              <FIELD INDEX="" CONTROL="N">
                <LBL>${FORM.SCREEN.0.BODY.TAB.SECTION.2.PART.2.FLDSET.FIELD.0.LBL}</LBL>
                <SIZE></SIZE>
                <CUSTOM>
                  <OFF>N</OFF>
                  <ON>Y</ON>
                </CUSTOM>
                <DTYPE>VARCHAR2</DTYPE>
                <COLS></COLS>
                <TYPE>CHECKBOX</TYPE>
                <CHECKED>N</CHECKED>
                <MAXLENGTH>1</MAXLENGTH>
                <NAME>ACCRREQ</NAME>
                <ROWS></ROWS>
              </FIELD>
              <FIELD INDEX="" CONTROL="N">
                <LBL>${FORM.SCREEN.0.BODY.TAB.SECTION.2.PART.2.FLDSET.FIELD.1.LBL}</LBL>
                <SIZE></SIZE>
                <OPTION VALUE="D" SELECTED="0">${FORM.SCREEN.0.BODY.TAB.SECTION.2.PART.2.FLDSET.FIELD.1.OPTION.0.#text}</OPTION>
                <OPTION VALUE="M" SELECTED="0">${FORM.SCREEN.0.BODY.TAB.SECTION.2.PART.2.FLDSET.FIELD.1.OPTION.1.#text}</OPTION>
                <OPTION VALUE="H" SELECTED="0">${FORM.SCREEN.0.BODY.TAB.SECTION.2.PART.2.FLDSET.FIELD.1.OPTION.2.#text}</OPTION>
                <OPTION VALUE="Q" SELECTED="0">${FORM.SCREEN.0.BODY.TAB.SECTION.2.PART.2.FLDSET.FIELD.1.OPTION.3.#text}</OPTION>
                <OPTION VALUE="Y" SELECTED="0">${FORM.SCREEN.0.BODY.TAB.SECTION.2.PART.2.FLDSET.FIELD.1.OPTION.4.#text}</OPTION>
                <OPTION VALUE="" SELECTED="-1"></OPTION>
                <DTYPE>VARCHAR2</DTYPE>
                <COLS></COLS>
                <TYPE>SELECT</TYPE>
                <MAXLENGTH>1</MAXLENGTH>
                <NAME>ACCRFREQ</NAME>
                <ROWS></ROWS>
              </FIELD>
              <FIELD CONTROL="N" INDEX="">
                <MAX_DECIMALS></MAX_DECIMALS>
                <SIZE></SIZE>
                <OPTION VALUE="1" SELECTED="0">${FORM.SCREEN.0.BODY.TAB.SECTION.2.PART.2.FLDSET.FIELD.2.OPTION.0.#text}</OPTION>
                <OPTION VALUE="2" SELECTED="0">${FORM.SCREEN.0.BODY.TAB.SECTION.2.PART.2.FLDSET.FIELD.2.OPTION.1.#text}</OPTION>
                <OPTION VALUE="3" SELECTED="0">${FORM.SCREEN.0.BODY.TAB.SECTION.2.PART.2.FLDSET.FIELD.2.OPTION.2.#text}</OPTION>
                <OPTION VALUE="4" SELECTED="0">${FORM.SCREEN.0.BODY.TAB.SECTION.2.PART.2.FLDSET.FIELD.2.OPTION.3.#text}</OPTION>
                <OPTION VALUE="5" SELECTED="0">${FORM.SCREEN.0.BODY.TAB.SECTION.2.PART.2.FLDSET.FIELD.2.OPTION.4.#text}</OPTION>
                <OPTION VALUE="6" SELECTED="0">${FORM.SCREEN.0.BODY.TAB.SECTION.2.PART.2.FLDSET.FIELD.2.OPTION.5.#text}</OPTION>
                <OPTION VALUE="7" SELECTED="0">${FORM.SCREEN.0.BODY.TAB.SECTION.2.PART.2.FLDSET.FIELD.2.OPTION.6.#text}</OPTION>
                <OPTION VALUE="8" SELECTED="0">${FORM.SCREEN.0.BODY.TAB.SECTION.2.PART.2.FLDSET.FIELD.2.OPTION.7.#text}</OPTION>
                <OPTION VALUE="9" SELECTED="0">${FORM.SCREEN.0.BODY.TAB.SECTION.2.PART.2.FLDSET.FIELD.2.OPTION.8.#text}</OPTION>
                <OPTION VALUE="10" SELECTED="0">${FORM.SCREEN.0.BODY.TAB.SECTION.2.PART.2.FLDSET.FIELD.2.OPTION.9.#text}</OPTION>
                <OPTION VALUE="11" SELECTED="0">${FORM.SCREEN.0.BODY.TAB.SECTION.2.PART.2.FLDSET.FIELD.2.OPTION.10.#text}</OPTION>
                <OPTION VALUE="12" SELECTED="0">${FORM.SCREEN.0.BODY.TAB.SECTION.2.PART.2.FLDSET.FIELD.2.OPTION.11.#text}</OPTION>
                <OPTION VALUE="" SELECTED="-1"></OPTION>
                <MAX_VAL></MAX_VAL>
                <COLS></COLS>
                <MAXLENGTH>22</MAXLENGTH>
                <NAME>ACCRSTMTH</NAME>
                <LBL>${FORM.SCREEN.0.BODY.TAB.SECTION.2.PART.2.FLDSET.FIELD.2.LBL}</LBL>
                <DTYPE>NUMBER</DTYPE>
                <TYPE>SELECT</TYPE>
                <MIN_VAL></MIN_VAL>
                <ROWS></ROWS>
              </FIELD>
              <FIELD CONTROL="N" INDEX="">
                <MAX_DECIMALS></MAX_DECIMALS>
                <SIZE></SIZE>
                <MAX_VAL>31</MAX_VAL>
                <COLS></COLS>
                <MAXLENGTH>22</MAXLENGTH>
                <NAME>ACCRSTDATE</NAME>
                <LBL>${FORM.SCREEN.0.BODY.TAB.SECTION.2.PART.2.FLDSET.FIELD.3.LBL}</LBL>
                <DTYPE>NUMBER</DTYPE>
                <TYPE>TEXT</TYPE>
                <MIN_VAL>1</MIN_VAL>
                <ROWS></ROWS>
              </FIELD>
              <LBL>${FORM.SCREEN.0.BODY.TAB.SECTION.2.PART.2.FLDSET.LBL}</LBL>
              <HREQ>0</HREQ>
              <BLOCK>BLK_COMPONENT_DET</BLOCK>
              <WIDTH></WIDTH>
              <HEIGHT></HEIGHT>
            </FLDSET>

          </PART>
          <LBL></LBL>

        </SECTION>
        <SECTION ID="SEC_COMP3" COLLAPSE="N">
          <PART NAME="PART1" ID="PART1" WIDTH="100">
            <FLDSET VIEW="ME" TYPE="ME" INDEX="1" ID="FST_DFLT_SCHEDULES">
              <FIELD CONTROL="N" INDEX="">
                <MAX_DECIMALS></MAX_DECIMALS>
                <SIZE></SIZE>
                <MAX_VAL></MAX_VAL>
                <COLS></COLS>
                <MAXLENGTH>22</MAXLENGTH>
                <NAME>SEQNO</NAME>
                <LBL>${FORM.SCREEN.0.BODY.TAB.SECTION.3.PART.FLDSET.FIELD.0.LBL}</LBL>
                <DTYPE>NUMBER</DTYPE>
                <TYPE>TEXT</TYPE>
                <MIN_VAL></MIN_VAL>
                <ROWS></ROWS>
              </FIELD>
              <FIELD INDEX="" CONTROL="N">
                <LBL>${FORM.SCREEN.0.BODY.TAB.SECTION.3.PART.FLDSET.FIELD.1.LBL}</LBL>
                <SIZE></SIZE>
                <OPTION VALUE="P" SELECTED="0">${FORM.SCREEN.0.BODY.TAB.SECTION.3.PART.FLDSET.FIELD.1.OPTION.0.#text}</OPTION>
                <OPTION VALUE="R" SELECTED="0">${FORM.SCREEN.0.BODY.TAB.SECTION.3.PART.FLDSET.FIELD.1.OPTION.1.#text}</OPTION>
                <OPTION VALUE="D" SELECTED="0">${FORM.SCREEN.0.BODY.TAB.SECTION.3.PART.FLDSET.FIELD.1.OPTION.2.#text}</OPTION>
                <OPTION VALUE="N" SELECTED="0">${FORM.SCREEN.0.BODY.TAB.SECTION.3.PART.FLDSET.FIELD.1.OPTION.3.#text}</OPTION>
                <OPTION VALUE="" SELECTED="-1"></OPTION>
                <DTYPE>VARCHAR2</DTYPE>
                <COLS></COLS>
                <TYPE>SELECT</TYPE>
                <MAXLENGTH>1</MAXLENGTH>
                <NAME>SCHTYPE</NAME>
                <ROWS></ROWS>
              </FIELD>
              <FIELD INDEX="" CONTROL="N">
                <LBL>${FORM.SCREEN.0.BODY.TAB.SECTION.3.PART.FLDSET.FIELD.2.LBL}</LBL>
                <SIZE>1</SIZE>
                <OPTION VALUE="V" SELECTED="0">${FORM.SCREEN.0.BODY.TAB.SECTION.3.PART.FLDSET.FIELD.2.OPTION.0.#text}</OPTION>
                <OPTION VALUE="" SELECTED="-1"></OPTION>
                <DTYPE>VARCHAR2</DTYPE>
                <COLS></COLS>
                <TYPE>SELECT</TYPE>
                <MAXLENGTH>1</MAXLENGTH>
                <NAME>STREF</NAME>
                <ROWS></ROWS>
              </FIELD>
              <FIELD INDEX="" CONTROL="N">
                <LBL>${FORM.SCREEN.0.BODY.TAB.SECTION.3.PART.FLDSET.FIELD.3.LBL}</LBL>
                <SIZE>1</SIZE>
                <OPTION VALUE="D" SELECTED="0">${FORM.SCREEN.0.BODY.TAB.SECTION.3.PART.FLDSET.FIELD.3.OPTION.0.#text}</OPTION>
                <OPTION VALUE="M" SELECTED="0">${FORM.SCREEN.0.BODY.TAB.SECTION.3.PART.FLDSET.FIELD.3.OPTION.1.#text}</OPTION>
                <OPTION VALUE="H" SELECTED="0">${FORM.SCREEN.0.BODY.TAB.SECTION.3.PART.FLDSET.FIELD.3.OPTION.2.#text}</OPTION>
                <OPTION VALUE="Q" SELECTED="0">${FORM.SCREEN.0.BODY.TAB.SECTION.3.PART.FLDSET.FIELD.3.OPTION.3.#text}</OPTION>
                <OPTION VALUE="Y" SELECTED="0">${FORM.SCREEN.0.BODY.TAB.SECTION.3.PART.FLDSET.FIELD.3.OPTION.4.#text}</OPTION>
                <OPTION VALUE="B" SELECTED="0">${FORM.SCREEN.0.BODY.TAB.SECTION.3.PART.FLDSET.FIELD.3.OPTION.5.#text}</OPTION>
                <OPTION VALUE="W" SELECTED="0">${FORM.SCREEN.0.BODY.TAB.SECTION.3.PART.FLDSET.FIELD.3.OPTION.6.#text}</OPTION>
                <OPTION VALUE="" SELECTED="-1"></OPTION>
                <DTYPE>VARCHAR2</DTYPE>
                <COLS></COLS>
                <TYPE>SELECT</TYPE>
                <MAXLENGTH>1</MAXLENGTH>
                <NAME>FRQUNIT</NAME>
                <ROWS></ROWS>
              </FIELD>
              <FIELD CONTROL="N" INDEX="">
                <MAX_DECIMALS></MAX_DECIMALS>
                <SIZE></SIZE>
                <MAX_VAL></MAX_VAL>
                <COLS></COLS>
                <MAXLENGTH>22</MAXLENGTH>
                <NAME>FREQ</NAME>
                <LBL>${FORM.SCREEN.0.BODY.TAB.SECTION.3.PART.FLDSET.FIELD.4.LBL}</LBL>
                <DTYPE>NUMBER</DTYPE>
                <TYPE>TEXT</TYPE>
                <MIN_VAL></MIN_VAL>
                <ROWS></ROWS>
              </FIELD>
              <FIELD INDEX="" CONTROL="N">
                <LBL>${FORM.SCREEN.0.BODY.TAB.SECTION.3.PART.FLDSET.FIELD.5.LBL}</LBL>
                <SIZE></SIZE>
                <OPTION VALUE="1" SELECTED="0">${FORM.SCREEN.0.BODY.TAB.SECTION.3.PART.FLDSET.FIELD.5.OPTION.0.#text}</OPTION>
                <OPTION VALUE="2" SELECTED="0">${FORM.SCREEN.0.BODY.TAB.SECTION.3.PART.FLDSET.FIELD.5.OPTION.1.#text}</OPTION>
                <OPTION VALUE="3" SELECTED="0">${FORM.SCREEN.0.BODY.TAB.SECTION.3.PART.FLDSET.FIELD.5.OPTION.2.#text}</OPTION>
                <OPTION VALUE="4" SELECTED="0">${FORM.SCREEN.0.BODY.TAB.SECTION.3.PART.FLDSET.FIELD.5.OPTION.3.#text}</OPTION>
                <OPTION VALUE="5" SELECTED="0">${FORM.SCREEN.0.BODY.TAB.SECTION.3.PART.FLDSET.FIELD.5.OPTION.4.#text}</OPTION>
                <OPTION VALUE="6" SELECTED="0">${FORM.SCREEN.0.BODY.TAB.SECTION.3.PART.FLDSET.FIELD.5.OPTION.5.#text}</OPTION>
                <OPTION VALUE="7" SELECTED="0">${FORM.SCREEN.0.BODY.TAB.SECTION.3.PART.FLDSET.FIELD.5.OPTION.6.#text}</OPTION>
                <OPTION VALUE="" SELECTED="-1"></OPTION>
                <DTYPE>VARCHAR2</DTYPE>
                <COLS></COLS>
                <TYPE>SELECT</TYPE>
                <MAXLENGTH>1</MAXLENGTH>
                <NAME>STARTDAY</NAME>
                <ROWS></ROWS>
              </FIELD>
              <FIELD CONTROL="N" INDEX="">
                <MAX_DECIMALS></MAX_DECIMALS>
                <SIZE></SIZE>
                <MAX_VAL></MAX_VAL>
                <COLS></COLS>
                <MAXLENGTH>11</MAXLENGTH>
                <NAME>STARTDT</NAME>
                <LBL>${FORM.SCREEN.0.BODY.TAB.SECTION.3.PART.FLDSET.FIELD.6.LBL}</LBL>
                <DTYPE>NUMBER</DTYPE>
                <TYPE>DATE</TYPE>
                <MIN_VAL></MIN_VAL>
                <ROWS></ROWS>
              </FIELD>
              <FIELD CONTROL="N" INDEX="">
                <MAX_DECIMALS></MAX_DECIMALS>
                <SIZE></SIZE>
                <OPTION VALUE="1" SELECTED="0">${FORM.SCREEN.0.BODY.TAB.SECTION.3.PART.FLDSET.FIELD.7.OPTION.0.#text}</OPTION>
                <OPTION VALUE="2" SELECTED="0">${FORM.SCREEN.0.BODY.TAB.SECTION.3.PART.FLDSET.FIELD.7.OPTION.1.#text}</OPTION>
                <OPTION VALUE="3" SELECTED="0">${FORM.SCREEN.0.BODY.TAB.SECTION.3.PART.FLDSET.FIELD.7.OPTION.2.#text}</OPTION>
                <OPTION VALUE="4" SELECTED="0">${FORM.SCREEN.0.BODY.TAB.SECTION.3.PART.FLDSET.FIELD.7.OPTION.3.#text}</OPTION>
                <OPTION VALUE="5" SELECTED="0">${FORM.SCREEN.0.BODY.TAB.SECTION.3.PART.FLDSET.FIELD.7.OPTION.4.#text}</OPTION>
                <OPTION VALUE="6" SELECTED="0">${FORM.SCREEN.0.BODY.TAB.SECTION.3.PART.FLDSET.FIELD.7.OPTION.5.#text}</OPTION>
                <OPTION VALUE="7" SELECTED="0">${FORM.SCREEN.0.BODY.TAB.SECTION.3.PART.FLDSET.FIELD.7.OPTION.6.#text}</OPTION>
                <OPTION VALUE="8" SELECTED="0">${FORM.SCREEN.0.BODY.TAB.SECTION.3.PART.FLDSET.FIELD.7.OPTION.7.#text}</OPTION>
                <OPTION VALUE="9" SELECTED="0">${FORM.SCREEN.0.BODY.TAB.SECTION.3.PART.FLDSET.FIELD.7.OPTION.8.#text}</OPTION>
                <OPTION VALUE="10" SELECTED="0">${FORM.SCREEN.0.BODY.TAB.SECTION.3.PART.FLDSET.FIELD.7.OPTION.9.#text}</OPTION>
                <OPTION VALUE="11" SELECTED="0">${FORM.SCREEN.0.BODY.TAB.SECTION.3.PART.FLDSET.FIELD.7.OPTION.10.#text}</OPTION>
                <OPTION VALUE="12" SELECTED="0">${FORM.SCREEN.0.BODY.TAB.SECTION.3.PART.FLDSET.FIELD.7.OPTION.11.#text}</OPTION>
                <OPTION VALUE="" SELECTED="-1"></OPTION>
                <MAX_VAL></MAX_VAL>
                <COLS></COLS>
                <MAXLENGTH>22</MAXLENGTH>
                <NAME>STARTMON</NAME>
                <LBL>${FORM.SCREEN.0.BODY.TAB.SECTION.3.PART.FLDSET.FIELD.7.LBL}</LBL>
                <DTYPE>NUMBER</DTYPE>
                <TYPE>SELECT</TYPE>
                <MIN_VAL></MIN_VAL>
                <ROWS></ROWS>
              </FIELD>
              <FIELD CONTROL="N" INDEX="">
                <MAX_DECIMALS></MAX_DECIMALS>
                <SIZE></SIZE>
                <MAX_VAL></MAX_VAL>
                <COLS></COLS>
                <MAXLENGTH>22</MAXLENGTH>
                <NAME>DUEON</NAME>
                <LBL>${FORM.SCREEN.0.BODY.TAB.SECTION.3.PART.FLDSET.FIELD.8.LBL}</LBL>
                <DTYPE>NUMBER</DTYPE>
                <TYPE>TEXT</TYPE>
                <MIN_VAL></MIN_VAL>
                <ROWS></ROWS>
              </FIELD>
              <FIELD INDEX="" CONTROL="N">
                <LBL>${FORM.SCREEN.0.BODY.TAB.SECTION.3.PART.FLDSET.FIELD.9.LBL}</LBL>
                <SIZE>1</SIZE>
                <OPTION VALUE="N" SELECTED="0">${FORM.SCREEN.0.BODY.TAB.SECTION.3.PART.FLDSET.FIELD.9.OPTION.0.#text}</OPTION>
                <OPTION VALUE="M" SELECTED="0">${FORM.SCREEN.0.BODY.TAB.SECTION.3.PART.FLDSET.FIELD.9.OPTION.1.#text}</OPTION>
                <OPTION VALUE="" SELECTED="-1"></OPTION>
                <DTYPE>VARCHAR2</DTYPE>
                <COLS></COLS>
                <TYPE>SELECT</TYPE>
                <MAXLENGTH>1</MAXLENGTH>
                <NAME>SCHFLAG</NAME>
                <ROWS></ROWS>
              </FIELD>
              <FIELD CONTROL="N" INDEX="">
                <MAX_DECIMALS></MAX_DECIMALS>
                <SIZE></SIZE>
                <MAX_VAL></MAX_VAL>
                <COLS></COLS>
                <MAXLENGTH>22</MAXLENGTH>
                <NAME>NOOFSCH</NAME>
                <LBL>${FORM.SCREEN.0.BODY.TAB.SECTION.3.PART.FLDSET.FIELD.10.LBL}</LBL>
                <DTYPE>NUMBER</DTYPE>
                <TYPE>TEXT</TYPE>
                <MIN_VAL></MIN_VAL>
                <ROWS></ROWS>
              </FIELD>
              <FIELD INDEX="" CONTROL="N">
                <LBL>${FORM.SCREEN.0.BODY.TAB.SECTION.3.PART.FLDSET.FIELD.11.LBL}</LBL>
                <SIZE></SIZE>
                <CUSTOM>
                  <OFF>N</OFF>
                  <ON>Y</ON>
                </CUSTOM>
                <DTYPE>VARCHAR2</DTYPE>
                <COLS></COLS>
                <TYPE>CHECKBOX</TYPE>
                <CHECKED>N</CHECKED>
                <MAXLENGTH>1</MAXLENGTH>
                <NAME>CAPTLD</NAME>
                <ROWS></ROWS>
              </FIELD>
              <FIELD INDEX="" CONTROL="N">
                <LBL>${FORM.SCREEN.0.BODY.TAB.SECTION.3.PART.FLDSET.FIELD.12.LBL}</LBL>
                <SIZE></SIZE>
                <DTYPE>VARCHAR2</DTYPE>
                <COLS></COLS>
                <TYPE>TEXT</TYPE>
                <MAXLENGTH>27</MAXLENGTH>
                <NAME>FORMULA</NAME>
                <ROWS></ROWS>
              </FIELD>
              <LBL>${FORM.SCREEN.0.BODY.TAB.SECTION.3.PART.FLDSET.LBL}</LBL>
              <HREQ>0</HREQ>
              <BLOCK>BLK_DFLT_SCHEDULES</BLOCK>
              <WIDTH></WIDTH>
              <PGSIZE>15</PGSIZE>
              <HEIGHT></HEIGHT>
            </FLDSET>

          </PART>
          <LBL></LBL>

        </SECTION>
      </TAB>
    </BODY>
  </SCREEN>
  <SCREEN MAIN_WIN="N" NAME="CVS_EXPR" POSITION="template" TITLE="${FORM.SCREEN.1.-TITLE}" TMP_SCR_TYPE="M">
    <EXIT_BTN>2</EXIT_BTN>
    <HEADER>
      <TAB ID="TAB_HEADER">
        <LBL></LBL>

      </TAB>
    </HEADER>
    <FOOTER>
      <TAB ID="TAB_FOOTER">
        <LBL></LBL>

      </TAB>
    </FOOTER>
    <BODY>
      <TAB ID="TAB_MAIN">
        <LBL></LBL>
        <SECTION ID="SEC_1" COLLAPSE="N">
          <PART NAME="PART1" ID="PART1" WIDTH="100">
            <FLDSET VIEW="SE" TYPE="ME" INDEX="1" ID="FST_EXPRB">
              <NAV_BTN_REQ>Y</NAV_BTN_REQ>
              <FIELD INDEX="" CONTROL="N" SPRT="1">
                <LBL>${FORM.SCREEN.1.BODY.TAB.SECTION.0.PART.FLDSET.FIELD.0.LBL}</LBL>
                <SIZE></SIZE>
                <DTYPE>VARCHAR2</DTYPE>
                <COLS></COLS>
                <TYPE>TEXT</TYPE>
                <MAXLENGTH>27</MAXLENGTH>
                <NAME>FORMULA</NAME>
                <CASE>UPPER</CASE>
                <ROWS></ROWS>
              </FIELD>
              <FIELD CONTROL="N" SPRT="2" INDEX="">
                <SIZE></SIZE>
                <OPTION VALUE="S" SELECTED="0">${FORM.SCREEN.1.BODY.TAB.SECTION.0.PART.FLDSET.FIELD.1.OPTION.0.#text}</OPTION>
                <OPTION VALUE="C" SELECTED="0">${FORM.SCREEN.1.BODY.TAB.SECTION.0.PART.FLDSET.FIELD.1.OPTION.1.#text}</OPTION>
                <OPTION VALUE="G" SELECTED="0">${FORM.SCREEN.1.BODY.TAB.SECTION.0.PART.FLDSET.FIELD.1.OPTION.2.#text}</OPTION>
                <OPTION VALUE="H" SELECTED="0">${FORM.SCREEN.1.BODY.TAB.SECTION.0.PART.FLDSET.FIELD.1.OPTION.3.#text}</OPTION>
                <OPTION VALUE="N" SELECTED="-1"></OPTION>
                <VALUE>N</VALUE>
                <COLS></COLS>
                <MAXLENGTH>1</MAXLENGTH>
                <NAME>PROFIT_ELEMENT</NAME>
                <LBL>${FORM.SCREEN.1.BODY.TAB.SECTION.0.PART.FLDSET.FIELD.1.LBL}</LBL>
                <DTYPE>VARCHAR2</DTYPE>
                <TYPE>SELECT</TYPE>
                <ROWS></ROWS>
              </FIELD>
              <FIELD CONTROL="N" SPRT="2" INDEX="">
                <SIZE></SIZE>
                <COLS></COLS>
                <CHECKED>N</CHECKED>
                <MAXLENGTH>1</MAXLENGTH>
                <NAME>AMORT</NAME>
                <LBL>${FORM.SCREEN.1.BODY.TAB.SECTION.0.PART.FLDSET.FIELD.2.LBL}</LBL>
                <CUSTOM>
                  <OFF>N</OFF>
                  <ON>Y</ON>
                </CUSTOM>
                <DTYPE>VARCHAR2</DTYPE>
                <TYPE>CHECKBOX</TYPE>
                <ROWS></ROWS>
              </FIELD>
              <FIELD CONTROL="N" SPRT="1" INDEX="">
                <MAX_DECIMALS></MAX_DECIMALS>
                <SIZE></SIZE>
                <MAX_VAL></MAX_VAL>
                <COLS></COLS>
                <MAXLENGTH>22</MAXLENGTH>
                <NAME>CMPDDAYS</NAME>
                <LBL>${FORM.SCREEN.1.BODY.TAB.SECTION.0.PART.FLDSET.FIELD.3.LBL}</LBL>
                <DTYPE>NUMBER</DTYPE>
                <TYPE>TEXT</TYPE>
                <MIN_VAL></MIN_VAL>
                <ROWS></ROWS>
              </FIELD>
              <FIELD INDEX="" CONTROL="N" SPRT="2">
                <LBL>${FORM.SCREEN.1.BODY.TAB.SECTION.0.PART.FLDSET.FIELD.4.LBL}</LBL>
                <SIZE>1</SIZE>
                <OPTION VALUE="PRINCIPAL" SELECTED="0">${FORM.SCREEN.1.BODY.TAB.SECTION.0.PART.FLDSET.FIELD.4.OPTION.0.#text}</OPTION>
                <OPTION VALUE="" SELECTED="-1"></OPTION>
                <DTYPE>VARCHAR2</DTYPE>
                <COLS></COLS>
                <TYPE>SELECT</TYPE>
                <MAXLENGTH>20</MAXLENGTH>
                <NAME>AMORTBASELEM</NAME>
                <ROWS></ROWS>
              </FIELD>
              <FIELD CONTROL="N" SPRT="1" INDEX="">
                <MAX_DECIMALS></MAX_DECIMALS>
                <SIZE></SIZE>
                <MAX_VAL></MAX_VAL>
                <COLS></COLS>
                <MAXLENGTH>22</MAXLENGTH>
                <NAME>CMPDMON</NAME>
                <LBL>${FORM.SCREEN.1.BODY.TAB.SECTION.0.PART.FLDSET.FIELD.5.LBL}</LBL>
                <DTYPE>NUMBER</DTYPE>
                <TYPE>TEXT</TYPE>
                <MIN_VAL></MIN_VAL>
                <ROWS></ROWS>
              </FIELD>
              <FIELD INDEX="" CONTROL="N" SPRT="2">
                <LBL>${FORM.SCREEN.1.BODY.TAB.SECTION.0.PART.FLDSET.FIELD.6.LBL}</LBL>
                <SIZE></SIZE>
                <OPTION VALUE="D" SELECTED="0">${FORM.SCREEN.1.BODY.TAB.SECTION.0.PART.FLDSET.FIELD.6.OPTION.0.#text}</OPTION>
                <OPTION VALUE="U" SELECTED="0">${FORM.SCREEN.1.BODY.TAB.SECTION.0.PART.FLDSET.FIELD.6.OPTION.1.#text}</OPTION>
                <OPTION VALUE="" SELECTED="-1"></OPTION>
                <DTYPE>VARCHAR2</DTYPE>
                <COLS></COLS>
                <TYPE>SELECT</TYPE>
                <MAXLENGTH>1</MAXLENGTH>
                <NAME>RNDUPDWN</NAME>
                <ROWS></ROWS>
              </FIELD>
              <FIELD CONTROL="N" SPRT="1" INDEX="">
                <MAX_DECIMALS></MAX_DECIMALS>
                <SIZE></SIZE>
                <MAX_VAL></MAX_VAL>
                <COLS></COLS>
                <MAXLENGTH>22</MAXLENGTH>
                <NAME>CMPDYR</NAME>
                <LBL>${FORM.SCREEN.1.BODY.TAB.SECTION.0.PART.FLDSET.FIELD.7.LBL}</LBL>
                <DTYPE>NUMBER</DTYPE>
                <TYPE>TEXT</TYPE>
                <MIN_VAL></MIN_VAL>
                <ROWS></ROWS>
              </FIELD>
              <FIELD CONTROL="N" SPRT="2" INDEX="">
                <MAX_DECIMALS></MAX_DECIMALS>
                <SIZE></SIZE>
                <MAX_VAL></MAX_VAL>
                <COLS></COLS>
                <MAXLENGTH>22</MAXLENGTH>
                <NAME>RNDUPTO</NAME>
                <LBL>${FORM.SCREEN.1.BODY.TAB.SECTION.0.PART.FLDSET.FIELD.8.LBL}</LBL>
                <DTYPE>NUMBER</DTYPE>
                <TYPE>TEXT</TYPE>
                <MIN_VAL></MIN_VAL>
                <ROWS></ROWS>
              </FIELD>
              <LBL></LBL>
              <HREQ>0</HREQ>
              <BLOCK>BLK_COMP_FRM_BOOK</BLOCK>
              <WIDTH></WIDTH>
              <HEIGHT></HEIGHT>
            </FLDSET>
            <SPRTCNT>2</SPRTCNT>

          </PART>
          <LBL></LBL>

        </SECTION>
        <SECTION ID="SEC_2" COLLAPSE="N">
          <PART NAME="PART2" ID="PART2" WIDTH="100">
            <FLDSET VIEW="ME" TYPE="ME" INDEX="1" ID="FST_BOOK_EXPR">
              <FIELD CONTROL="N" INDEX="">
                <MAX_DECIMALS></MAX_DECIMALS>
                <SIZE></SIZE>
                <MAX_VAL></MAX_VAL>
                <COLS></COLS>
                <MAXLENGTH>22</MAXLENGTH>
                <NAME>EXPRLINE</NAME>
                <LBL>${FORM.SCREEN.1.BODY.TAB.SECTION.1.PART.FLDSET.FIELD.0.LBL}</LBL>
                <DTYPE>NUMBER</DTYPE>
                <TYPE>TEXT</TYPE>
                <MIN_VAL></MIN_VAL>
                <ROWS></ROWS>
              </FIELD>
              <FIELD INDEX="" CONTROL="N">
                <LBL>${FORM.SCREEN.1.BODY.TAB.SECTION.1.PART.FLDSET.FIELD.1.LBL}</LBL>
                <SIZE></SIZE>
                <DTYPE>VARCHAR2</DTYPE>
                <COLS></COLS>
                <TYPE>TEXT</TYPE>
                <MAXLENGTH>4000</MAXLENGTH>
                <NAME>COND</NAME>
                <CASE>UPPER</CASE>
                <ROWS></ROWS>
              </FIELD>
              <FIELD INDEX="" CONTROL="N">
                <POPUPEDIT>
                  <OK_IMG_SRC></OK_IMG_SRC>
                  <TITLE>${FORM.SCREEN.1.BODY.TAB.SECTION.1.PART.FLDSET.FIELD.2.POPUPEDIT.TITLE}</TITLE>
                  <CANCEL_IMG_SRC></CANCEL_IMG_SRC>
                </POPUPEDIT>
                <LBL>${FORM.SCREEN.1.BODY.TAB.SECTION.1.PART.FLDSET.FIELD.2.LBL}</LBL>
                <SIZE></SIZE>
                <DTYPE>VARCHAR2</DTYPE>
                <COLS></COLS>
                <TYPE>TEXT</TYPE>
                <MAXLENGTH>2000</MAXLENGTH>
                <NAME>RESULT</NAME>
                <ROWS></ROWS>
              </FIELD>
              <FIELD INDEX="" CONTROL="N">
                <LBL>${FORM.SCREEN.1.BODY.TAB.SECTION.1.PART.FLDSET.FIELD.3.LBL}</LBL>
                <SIZE></SIZE>
                <HIDDEN>-1</HIDDEN>
                <DTYPE>VARCHAR2</DTYPE>
                <VALUE>N</VALUE>
                <COLS></COLS>
                <TYPE>HIDDEN</TYPE>
                <MAXLENGTH>1</MAXLENGTH>
                <NAME>EXPRTYPE</NAME>
                <ROWS></ROWS>
              </FIELD>
              <FIELD INDEX="" CONTROL="N">
                <LBL>${FORM.SCREEN.1.BODY.TAB.SECTION.1.PART.FLDSET.FIELD.4.LBL}</LBL>
                <SIZE></SIZE>
                <DTYPE>VARCHAR2</DTYPE>
                <VALUE>B</VALUE>
                <COLS></COLS>
                <TYPE>TEXT</TYPE>
                <MAXLENGTH>1</MAXLENGTH>
                <NAME>FRMTYPE</NAME>
                <ROWS></ROWS>
              </FIELD>
              <LBL>${FORM.SCREEN.1.BODY.TAB.SECTION.1.PART.FLDSET.LBL}</LBL>
              <HREQ>0</HREQ>
              <BLOCK>BLK_BOOK_EXPR</BLOCK>
              <WIDTH></WIDTH>
              <PGSIZE>15</PGSIZE>
              <HEIGHT></HEIGHT>
            </FLDSET>

          </PART>
          <LBL></LBL>

        </SECTION>
      </TAB>
    </BODY>
  </SCREEN>
  <SCREEN MAIN_WIN="N" NAME="CVS_I_EXPR" POSITION="template" TITLE="${FORM.SCREEN.2.-TITLE}" TMP_SCR_TYPE="M">
    <EXIT_BTN>2</EXIT_BTN>
    <HEADER>
      <TAB ID="TAB_HEADER">
        <LBL></LBL>

      </TAB>
    </HEADER>
    <FOOTER>
      <TAB ID="TAB_FOOTER">
        <LBL></LBL>

      </TAB>
    </FOOTER>
    <BODY>
      <TAB ID="TAB_MAIN">
        <LBL></LBL>
        <SECTION ID="SEC_1" COLLAPSE="N">
          <PART NAME="PART1" ID="PART1" WIDTH="100">
            <FLDSET VIEW="SE" TYPE="ME" INDEX="1" ID="FST_EXPRI">
              <NAV_BTN_REQ>Y</NAV_BTN_REQ>
              <FIELD INDEX="" CONTROL="N" SPRT="1">
                <LBL>${FORM.SCREEN.2.BODY.TAB.SECTION.0.PART.FLDSET.FIELD.0.LBL}</LBL>
                <SIZE></SIZE>
                <DTYPE>VARCHAR2</DTYPE>
                <COLS></COLS>
                <TYPE>TEXT</TYPE>
                <MAXLENGTH>27</MAXLENGTH>
                <NAME>FORMULA</NAME>
                <CASE>UPPER</CASE>
                <ROWS></ROWS>
              </FIELD>
              <FIELD INDEX="" CONTROL="N" SPRT="2">
                <LBL>${FORM.SCREEN.2.BODY.TAB.SECTION.0.PART.FLDSET.FIELD.1.LBL}</LBL>
                <SIZE></SIZE>
                <DTYPE>VARCHAR2</DTYPE>
                <COLS></COLS>
                <TYPE>TEXT</TYPE>
                <MAXLENGTH>1</MAXLENGTH>
                <NAME>RNDUPDWN</NAME>
                <ROWS></ROWS>
              </FIELD>
              <FIELD CONTROL="N" SPRT="2" INDEX="">
                <MAX_DECIMALS></MAX_DECIMALS>
                <SIZE></SIZE>
                <MAX_VAL></MAX_VAL>
                <COLS></COLS>
                <MAXLENGTH>22</MAXLENGTH>
                <NAME>RNDUPTO</NAME>
                <LBL>${FORM.SCREEN.2.BODY.TAB.SECTION.0.PART.FLDSET.FIELD.2.LBL}</LBL>
                <DTYPE>NUMBER</DTYPE>
                <TYPE>TEXT</TYPE>
                <MIN_VAL></MIN_VAL>
                <ROWS></ROWS>
              </FIELD>
              <FIELD CONTROL="N" SPRT="1" INDEX="">
                <MAX_DECIMALS></MAX_DECIMALS>
                <SIZE></SIZE>
                <MAX_VAL></MAX_VAL>
                <COLS></COLS>
                <MAXLENGTH>22</MAXLENGTH>
                <NAME>CMPDDAYS</NAME>
                <LBL>${FORM.SCREEN.2.BODY.TAB.SECTION.0.PART.FLDSET.FIELD.3.LBL}</LBL>
                <DTYPE>NUMBER</DTYPE>
                <TYPE>TEXT</TYPE>
                <MIN_VAL></MIN_VAL>
                <ROWS></ROWS>
              </FIELD>
              <FIELD CONTROL="N" SPRT="1" INDEX="">
                <MAX_DECIMALS></MAX_DECIMALS>
                <SIZE></SIZE>
                <MAX_VAL></MAX_VAL>
                <COLS></COLS>
                <MAXLENGTH>22</MAXLENGTH>
                <NAME>CMPDMON</NAME>
                <LBL>${FORM.SCREEN.2.BODY.TAB.SECTION.0.PART.FLDSET.FIELD.4.LBL}</LBL>
                <DTYPE>NUMBER</DTYPE>
                <TYPE>TEXT</TYPE>
                <MIN_VAL></MIN_VAL>
                <ROWS></ROWS>
              </FIELD>
              <FIELD CONTROL="N" SPRT="1" INDEX="">
                <MAX_DECIMALS></MAX_DECIMALS>
                <SIZE></SIZE>
                <MAX_VAL></MAX_VAL>
                <COLS></COLS>
                <MAXLENGTH>22</MAXLENGTH>
                <NAME>CMPDYR</NAME>
                <LBL>${FORM.SCREEN.2.BODY.TAB.SECTION.0.PART.FLDSET.FIELD.5.LBL}</LBL>
                <DTYPE>NUMBER</DTYPE>
                <TYPE>TEXT</TYPE>
                <MIN_VAL></MIN_VAL>
                <ROWS></ROWS>
              </FIELD>
              <LBL></LBL>
              <HREQ>0</HREQ>
              <BLOCK>BLK_COMP_FRM_INTERMEDIATE</BLOCK>
              <WIDTH></WIDTH>
              <HEIGHT></HEIGHT>
            </FLDSET>
            <SPRTCNT>2</SPRTCNT>

          </PART>
          <LBL></LBL>

        </SECTION>
        <SECTION ID="SEC_2" COLLAPSE="N">
          <PART NAME="PART1" ID="PART1" WIDTH="100">
            <FLDSET VIEW="ME" TYPE="ME" INDEX="1" ID="FST_INTERMEDIATE_EXPR">
              <FIELD CONTROL="N" INDEX="">
                <MAX_DECIMALS></MAX_DECIMALS>
                <SIZE></SIZE>
                <MAX_VAL></MAX_VAL>
                <COLS></COLS>
                <MAXLENGTH>22</MAXLENGTH>
                <NAME>EXPRLINE</NAME>
                <LBL>${FORM.SCREEN.2.BODY.TAB.SECTION.1.PART.FLDSET.FIELD.0.LBL}</LBL>
                <DTYPE>NUMBER</DTYPE>
                <TYPE>TEXT</TYPE>
                <MIN_VAL></MIN_VAL>
                <ROWS></ROWS>
              </FIELD>
              <FIELD INDEX="" CONTROL="N">
                <LBL>${FORM.SCREEN.2.BODY.TAB.SECTION.1.PART.FLDSET.FIELD.1.LBL}</LBL>
                <SIZE></SIZE>
                <DTYPE>VARCHAR2</DTYPE>
                <COLS></COLS>
                <TYPE>TEXT</TYPE>
                <MAXLENGTH>4000</MAXLENGTH>
                <NAME>COND</NAME>
                <CASE>UPPER</CASE>
                <ROWS></ROWS>
              </FIELD>
              <FIELD INDEX="" CONTROL="N">
                <POPUPEDIT>
                  <OK_IMG_SRC></OK_IMG_SRC>
                  <TITLE>${FORM.SCREEN.2.BODY.TAB.SECTION.1.PART.FLDSET.FIELD.2.POPUPEDIT.TITLE}</TITLE>
                  <CANCEL_IMG_SRC></CANCEL_IMG_SRC>
                </POPUPEDIT>
                <LBL>${FORM.SCREEN.2.BODY.TAB.SECTION.1.PART.FLDSET.FIELD.2.LBL}</LBL>
                <SIZE></SIZE>
                <DTYPE>VARCHAR2</DTYPE>
                <COLS></COLS>
                <TYPE>TEXT</TYPE>
                <MAXLENGTH>2000</MAXLENGTH>
                <NAME>RESULT</NAME>
                <ROWS></ROWS>
              </FIELD>
              <FIELD INDEX="" CONTROL="N">
                <LBL>${FORM.SCREEN.2.BODY.TAB.SECTION.1.PART.FLDSET.FIELD.3.LBL}</LBL>
                <SIZE></SIZE>
                <HIDDEN>-1</HIDDEN>
                <DTYPE>VARCHAR2</DTYPE>
                <VALUE>N</VALUE>
                <COLS></COLS>
                <TYPE>HIDDEN</TYPE>
                <MAXLENGTH>1</MAXLENGTH>
                <NAME>EXPRTYPE</NAME>
                <ROWS></ROWS>
              </FIELD>
              <FIELD INDEX="" CONTROL="N">
                <LBL>${FORM.SCREEN.2.BODY.TAB.SECTION.1.PART.FLDSET.FIELD.4.LBL}</LBL>
                <SIZE></SIZE>
                <DTYPE>VARCHAR2</DTYPE>
                <VALUE>I</VALUE>
                <COLS></COLS>
                <TYPE>TEXT</TYPE>
                <MAXLENGTH>1</MAXLENGTH>
                <NAME>FRMTYPE</NAME>
                <ROWS></ROWS>
              </FIELD>
              <LBL>${FORM.SCREEN.2.BODY.TAB.SECTION.1.PART.FLDSET.LBL}</LBL>
              <HREQ>0</HREQ>
              <BLOCK>BLK_INTERMEDIATE_EXPR</BLOCK>
              <WIDTH></WIDTH>
              <PGSIZE>15</PGSIZE>
              <HEIGHT></HEIGHT>
            </FLDSET>

          </PART>
          <LBL></LBL>

        </SECTION>
      </TAB>
    </BODY>
  </SCREEN>
  <SCREEN MAIN_WIN="N" NAME="CVS_M_EXPR" POSITION="template" TITLE="${FORM.SCREEN.3.-TITLE}" TMP_SCR_TYPE="M">
    <EXIT_BTN>2</EXIT_BTN>
    <HEADER>
      <TAB ID="TAB_HEADER">
        <LBL></LBL>

      </TAB>
    </HEADER>
    <FOOTER>
      <TAB ID="TAB_FOOTER">
        <LBL></LBL>

      </TAB>
    </FOOTER>
    <BODY>
      <TAB ID="TAB_MAIN">
        <LBL></LBL>
        <SECTION ID="SEC_1" COLLAPSE="N">
          <PART NAME="PART1" ID="PART1" WIDTH="100">
            <FLDSET VIEW="SE" TYPE="ME" INDEX="1" ID="FST_EXPRM">
              <NAV_BTN_REQ>Y</NAV_BTN_REQ>
              <FIELD INDEX="" CONTROL="N" SPRT="1">
                <LBL>${FORM.SCREEN.3.BODY.TAB.SECTION.0.PART.FLDSET.FIELD.0.LBL}</LBL>
                <SIZE></SIZE>
                <DTYPE>VARCHAR2</DTYPE>
                <COLS></COLS>
                <TYPE>TEXT</TYPE>
                <MAXLENGTH>27</MAXLENGTH>
                <NAME>FORMULA</NAME>
                <CASE>UPPER</CASE>
                <ROWS></ROWS>
              </FIELD>
              <FIELD CONTROL="N" SPRT="2" INDEX="">
                <SIZE></SIZE>
                <COLS></COLS>
                <CHECKED>N</CHECKED>
                <MAXLENGTH>1</MAXLENGTH>
                <NAME>MORLIQFRM</NAME>
                <LBL>${FORM.SCREEN.3.BODY.TAB.SECTION.0.PART.FLDSET.FIELD.1.LBL}</LBL>
                <CUSTOM>
                  <OFF>N</OFF>
                  <ON>Y</ON>
                </CUSTOM>
                <DTYPE>VARCHAR2</DTYPE>
                <TYPE>CHECKBOX</TYPE>
                <ROWS></ROWS>
              </FIELD>
              <FIELD CONTROL="N" SPRT="2" INDEX="">
                <SIZE></SIZE>
                <COLS></COLS>
                <CHECKED>N</CHECKED>
                <MAXLENGTH>1</MAXLENGTH>
                <NAME>LIQMORTOEMI</NAME>
                <LBL>${FORM.SCREEN.3.BODY.TAB.SECTION.0.PART.FLDSET.FIELD.2.LBL}</LBL>
                <CUSTOM>
                  <OFF>N</OFF>
                  <ON>Y</ON>
                </CUSTOM>
                <DTYPE>VARCHAR2</DTYPE>
                <TYPE>CHECKBOX</TYPE>
                <ROWS></ROWS>
              </FIELD>
              <FIELD CONTROL="N" SPRT="1" INDEX="">
                <MAX_DECIMALS></MAX_DECIMALS>
                <SIZE></SIZE>
                <MAX_VAL></MAX_VAL>
                <COLS></COLS>
                <MAXLENGTH>22</MAXLENGTH>
                <NAME>CMPDDAYS</NAME>
                <LBL>${FORM.SCREEN.3.BODY.TAB.SECTION.0.PART.FLDSET.FIELD.3.LBL}</LBL>
                <DTYPE>NUMBER</DTYPE>
                <TYPE>TEXT</TYPE>
                <MIN_VAL></MIN_VAL>
                <ROWS></ROWS>
              </FIELD>
              <FIELD CONTROL="N" SPRT="1" INDEX="">
                <MAX_DECIMALS></MAX_DECIMALS>
                <SIZE></SIZE>
                <MAX_VAL></MAX_VAL>
                <COLS></COLS>
                <MAXLENGTH>22</MAXLENGTH>
                <NAME>CMPDMON</NAME>
                <LBL>${FORM.SCREEN.3.BODY.TAB.SECTION.0.PART.FLDSET.FIELD.4.LBL}</LBL>
                <DTYPE>NUMBER</DTYPE>
                <TYPE>TEXT</TYPE>
                <MIN_VAL></MIN_VAL>
                <ROWS></ROWS>
              </FIELD>
              <FIELD CONTROL="N" SPRT="1" INDEX="">
                <MAX_DECIMALS></MAX_DECIMALS>
                <SIZE></SIZE>
                <MAX_VAL></MAX_VAL>
                <COLS></COLS>
                <MAXLENGTH>22</MAXLENGTH>
                <NAME>CMPDYR</NAME>
                <LBL>${FORM.SCREEN.3.BODY.TAB.SECTION.0.PART.FLDSET.FIELD.5.LBL}</LBL>
                <DTYPE>NUMBER</DTYPE>
                <TYPE>TEXT</TYPE>
                <MIN_VAL></MIN_VAL>
                <ROWS></ROWS>
              </FIELD>
              <FIELD CONTROL="N" SPRT="2" INDEX="">
                <SIZE></SIZE>
                <VALUE>Y</VALUE>
                <COLS></COLS>
                <CHECKED>-1</CHECKED>
                <MAXLENGTH>1</MAXLENGTH>
                <NAME>DFLTMORFRM</NAME>
                <LBL>${FORM.SCREEN.3.BODY.TAB.SECTION.0.PART.FLDSET.FIELD.6.LBL}</LBL>
                <CUSTOM>
                  <OFF>N</OFF>
                  <ON>Y</ON>
                </CUSTOM>
                <DTYPE>VARCHAR2</DTYPE>
                <TYPE>CHECKBOX</TYPE>
                <ROWS></ROWS>
              </FIELD>
              <FIELD INDEX="" CONTROL="N" SPRT="2">
                <LBL>${FORM.SCREEN.3.BODY.TAB.SECTION.0.PART.FLDSET.FIELD.7.LBL}</LBL>
                <SIZE></SIZE>
                <DTYPE>VARCHAR2</DTYPE>
                <COLS></COLS>
                <TYPE>TEXT</TYPE>
                <MAXLENGTH>1</MAXLENGTH>
                <NAME>RNDUPDWN</NAME>
                <ROWS></ROWS>
              </FIELD>
              <FIELD CONTROL="N" SPRT="2" INDEX="">
                <MAX_DECIMALS></MAX_DECIMALS>
                <SIZE></SIZE>
                <MAX_VAL></MAX_VAL>
                <COLS></COLS>
                <MAXLENGTH>22</MAXLENGTH>
                <NAME>RNDUPTO</NAME>
                <LBL>${FORM.SCREEN.3.BODY.TAB.SECTION.0.PART.FLDSET.FIELD.8.LBL}</LBL>
                <DTYPE>NUMBER</DTYPE>
                <TYPE>TEXT</TYPE>
                <MIN_VAL></MIN_VAL>
                <ROWS></ROWS>
              </FIELD>
              <LBL></LBL>
              <HREQ>0</HREQ>
              <BLOCK>BLK_COMP_FRM_MORATORIUM</BLOCK>
              <WIDTH></WIDTH>
              <HEIGHT></HEIGHT>
            </FLDSET>
            <SPRTCNT>2</SPRTCNT>

          </PART>
          <LBL></LBL>

        </SECTION>
        <SECTION ID="SEC_2" COLLAPSE="N">
          <PART NAME="PART2" ID="PART2" WIDTH="100">
            <FLDSET VIEW="ME" TYPE="ME" INDEX="1" ID="FST_MORATORIUM_EXPR">
              <FIELD CONTROL="N" INDEX="">
                <MAX_DECIMALS></MAX_DECIMALS>
                <SIZE></SIZE>
                <MAX_VAL></MAX_VAL>
                <COLS></COLS>
                <MAXLENGTH>22</MAXLENGTH>
                <NAME>EXPRLINE</NAME>
                <LBL>${FORM.SCREEN.3.BODY.TAB.SECTION.1.PART.FLDSET.FIELD.0.LBL}</LBL>
                <DTYPE>NUMBER</DTYPE>
                <TYPE>TEXT</TYPE>
                <MIN_VAL></MIN_VAL>
                <ROWS></ROWS>
              </FIELD>
              <FIELD INDEX="" CONTROL="N">
                <LBL>${FORM.SCREEN.3.BODY.TAB.SECTION.1.PART.FLDSET.FIELD.1.LBL}</LBL>
                <SIZE></SIZE>
                <DTYPE>VARCHAR2</DTYPE>
                <COLS></COLS>
                <TYPE>TEXT</TYPE>
                <MAXLENGTH>4000</MAXLENGTH>
                <NAME>COND</NAME>
                <CASE>UPPER</CASE>
                <ROWS></ROWS>
              </FIELD>
              <FIELD INDEX="" CONTROL="N">
                <POPUPEDIT>
                  <OK_IMG_SRC></OK_IMG_SRC>
                  <TITLE>${FORM.SCREEN.3.BODY.TAB.SECTION.1.PART.FLDSET.FIELD.2.POPUPEDIT.TITLE}</TITLE>
                  <CANCEL_IMG_SRC></CANCEL_IMG_SRC>
                </POPUPEDIT>
                <LBL>${FORM.SCREEN.3.BODY.TAB.SECTION.1.PART.FLDSET.FIELD.2.LBL}</LBL>
                <SIZE></SIZE>
                <DTYPE>VARCHAR2</DTYPE>
                <COLS></COLS>
                <TYPE>TEXT</TYPE>
                <MAXLENGTH>2000</MAXLENGTH>
                <NAME>RESULT</NAME>
                <ROWS></ROWS>
              </FIELD>
              <FIELD INDEX="" CONTROL="N">
                <LBL>${FORM.SCREEN.3.BODY.TAB.SECTION.1.PART.FLDSET.FIELD.3.LBL}</LBL>
                <SIZE></SIZE>
                <HIDDEN>-1</HIDDEN>
                <DTYPE>VARCHAR2</DTYPE>
                <VALUE>N</VALUE>
                <COLS></COLS>
                <TYPE>HIDDEN</TYPE>
                <MAXLENGTH>1</MAXLENGTH>
                <NAME>EXPRTYPE</NAME>
                <ROWS></ROWS>
              </FIELD>
              <FIELD INDEX="" CONTROL="N">
                <LBL>${FORM.SCREEN.3.BODY.TAB.SECTION.1.PART.FLDSET.FIELD.4.LBL}</LBL>
                <SIZE></SIZE>
                <DTYPE>VARCHAR2</DTYPE>
                <COLS></COLS>
                <TYPE>TEXT</TYPE>
                <MAXLENGTH>1</MAXLENGTH>
                <NAME>FRMTYPE</NAME>
                <ROWS></ROWS>
              </FIELD>
              <LBL>${FORM.SCREEN.3.BODY.TAB.SECTION.1.PART.FLDSET.LBL}</LBL>
              <HREQ>0</HREQ>
              <BLOCK>BLK_MORATORIUM_EXPR</BLOCK>
              <WIDTH></WIDTH>
              <PGSIZE>15</PGSIZE>
              <HEIGHT></HEIGHT>
            </FLDSET>

          </PART>
          <LBL></LBL>

        </SECTION>
      </TAB>
    </BODY>
  </SCREEN>
</FORM>